Workbook

Sheet 00_Portada
B2: GENTIA
B5: PLAN DE IMPLEMENTACIÓN DEL ERP
B7: Hoja de ruta integral, control de avance y evidencia de aceptación
B9: Proyecto | C9: Implementación ERP GENTIA
B10: Versión | C10: 1.0
B11: Fecha de elaboración | C11: 46323.75
B12: Inicio base editable | C12: 46328.75
B13: Salida objetivo editable | C13: 46496.75
B14: Estrategia sugerida | C14: Rollout por olas: piloto → filiales prioritarias → resto del grupo
B15: Responsables | C15: Roles sugeridos; el cliente debe confirmar nombres y disponibilidad
B16: Subsidiarias incluidas | C16: 35
B17: Actividades detalladas | C17: 280
B18: Referencia | C18: Implementacion 2026 - GENTIA.xlsx
B21: SUPUESTOS EDITABLES Y REGLAS DE USO
B22: 1. Confirme las fechas, responsables y olas antes de aprobar la línea base.
B23: 2. Actualice Estado y % avance; el Dashboard se recalcula al abrir Excel.
B24: 3. No sobrescriba fórmulas de Duración, Semáforo, diferencias ni porcentajes.
B25: 4. Go-Live exige Mayor cuadrado, auxiliares conciliados en 0,00, UAT aprobada y cero defectos críticos.
B26: 5. Adjunte evidencia verificable para cada actividad, carga, prueba, hito y decisión.

Sheet 01_Dashboard
A1: DASHBOARD EJECUTIVO
A2: Indicadores dinámicos de avance, pruebas, riesgos y filiales.
A5: Actividades | C5: Completadas | E5: Avance | G5: Vencidas
A6: =COUNTA('02_Plan_Maestro'!$A$6:$A$285) -> 280 | C6: =COUNTIF('02_Plan_Maestro'!$V$6:$V$285,"Completada") -> 0 | E6: =IFERROR(SUMPRODUCT('02_Plan_Maestro'!$P$6:$P$285,'02_Plan_Maestro'!$W$6:$W$285)/SUM('02_Plan_Maestro'!$P$6:$P$285),0) -> 0 | G6: =COUNTIFS('02_Plan_Maestro'!$R$6:$R$285,"<"&TODAY(),'02_Plan_Maestro'!$V$6:$V$285,"<>Completada") -> 0
A9: Bloqueadas | C9: Riesgos críticos | E9: UAT | G9: Preparación filiales
A10: =COUNTIF('02_Plan_Maestro'!$V$6:$V$285,"Bloqueada") -> 0 | C10: =COUNTIFS('09_Riesgos'!$L$6:$L$40,">=15",'09_Riesgos'!$N$6:$N$40,"<>Cerrado") -> 0 | E10: =IFERROR(COUNTIF('06_Pruebas_UAT'!$K$6:$K$300,"Aprobado")/236,0) -> 0 | G10: =IFERROR(AVERAGE('03_Rollout_Filiales'!$M$6:$M$40),0) -> 0
A14: AVANCE POR MÓDULO
A15: Módulo | B15: Total | C15: Completadas | D15: Avance | E15: Vencidas | G15: Módulo | H15: Total | I15: Completadas | J15: Avance
A16: Gobierno del proyecto | B16: =COUNTIF('02_Plan_Maestro'!$C$6:$C$285,A16) -> 0 | C16: =COUNTIFS('02_Plan_Maestro'!$C$6:$C$285,A16,'02_Plan_Maestro'!$V$6:$V$285,"Completada") -> 0 | D16: =IFERROR(SUMPRODUCT(('02_Plan_Maestro'!$C$6:$C$285=A16)*'02_Plan_Maestro'!$P$6:$P$285*'02_Plan_Maestro'!$W$6:$W$285)/SUMIF('02_Plan_Maestro'!$C$6:$C$285,A16,'02_Plan_Maestro'!$P$6:$P$285),0) -> 0 | E16: =COUNTIFS('02_Plan_Maestro'!$C$6:$C$285,A16,'02_Plan_Maestro'!$R$6:$R$285,"<"&TODAY(),'02_Plan_Maestro'!$V$6:$V$285,"<>Completada") -> 0 | G16: Infraestructura y plataforma | H16: =COUNTIF('02_Plan_Maestro'!$C$6:$C$285,G16) -> 0 | I16: =COUNTIFS('02_Plan_Maestro'!$C$6:$C$285,G16,'02_Plan_Maestro'!$V$6:$V$285,"Completada") -> 0 | J16: =IFERROR(SUMPRODUCT(('02_Plan_Maestro'!$C$6:$C$285=G16)*'02_Plan_Maestro'!$P$6:$P$285*'02_Plan_Maestro'!$W$6:$W$285)/SUMIF('02_Plan_Maestro'!$C$6:$C$285,G16,'02_Plan_Maestro'!$P$6:$P$285),0) -> 0
A17: CORE | B17: =COUNTIF('02_Plan_Maestro'!$C$6:$C$285,A17) -> 0 | C17: =COUNTIFS('02_Plan_Maestro'!$C$6:$C$285,A17,'02_Plan_Maestro'!$V$6:$V$285,"Completada") -> 0 | D17: =IFERROR(SUMPRODUCT(('02_Plan_Maestro'!$C$6:$C$285=A17)*'02_Plan_Maestro'!$P$6:$P$285*'02_Plan_Maestro'!$W$6:$W$285)/SUMIF('02_Plan_Maestro'!$C$6:$C$285,A17,'02_Plan_Maestro'!$P$6:$P$285),0) -> 0 | E17: =COUNTIFS('02_Plan_Maestro'!$C$6:$C$285,A17,'02_Plan_Maestro'!$R$6:$R$285,"<"&TODAY(),'02_Plan_Maestro'!$V$6:$V$285,"<>Completada") -> 0 | G17: Organización | H17: =COUNTIF('02_Plan_Maestro'!$C$6:$C$285,G17) -> 0 | I17: =COUNTIFS('02_Plan_Maestro'!$C$6:$C$285,G17,'02_Plan_Maestro'!$V$6:$V$285,"Completada") -> 0 | J17: =IFERROR(SUMPRODUCT(('02_Plan_Maestro'!$C$6:$C$285=G17)*'02_Plan_Maestro'!$P$6:$P$285*'02_Plan_Maestro'!$W$6:$W$285)/SUMIF('02_Plan_Maestro'!$C$6:$C$285,G17,'02_Plan_Maestro'!$P$6:$P$285),0) -> 0
A18: Seguridad | B18: =COUNTIF('02_Plan_Maestro'!$C$6:$C$285,A18) -> 0 | C18: =COUNTIFS('02_Plan_Maestro'!$C$6:$C$285,A18,'02_Plan_Maestro'!$V$6:$V$285,"Completada") -> 0 | D18: =IFERROR(SUMPRODUCT(('02_Plan_Maestro'!$C$6:$C$285=A18)*'02_Plan_Maestro'!$P$6:$P$285*'02_Plan_Maestro'!$W$6:$W$285)/SUMIF('02_Plan_Maestro'!$C$6:$C$285,A18,'02_Plan_Maestro'!$P$6:$P$285),0) -> 0 | E18: =COUNTIFS('02_Plan_Maestro'!$C$6:$C$285,A18,'02_Plan_Maestro'!$R$6:$R$285,"<"&TODAY(),'02_Plan_Maestro'!$V$6:$V$285,"<>Completada") -> 0 | G18: Configuración transversal | H18: =COUNTIF('02_Plan_Maestro'!$C$6:$C$285,G18) -> 0 | I18: =COUNTIFS('02_Plan_Maestro'!$C$6:$C$285,G18,'02_Plan_Maestro'!$V$6:$V$285,"Completada") -> 0 | J18: =IFERROR(SUMPRODUCT(('02_Plan_Maestro'!$C$6:$C$285=G18)*'02_Plan_Maestro'!$P$6:$P$285*'02_Plan_Maestro'!$W$6:$W$285)/SUMIF('02_Plan_Maestro'!$C$6:$C$285,G18,'02_Plan_Maestro'!$P$6:$P$285),0) -> 0
A19: Contabilidad | B19: =COUNTIF('02_Plan_Maestro'!$C$6:$C$285,A19) -> 0 | C19: =COUNTIFS('02_Plan_Maestro'!$C$6:$C$285,A19,'02_Plan_Maestro'!$V$6:$V$285,"Completada") -> 0 | D19: =IFERROR(SUMPRODUCT(('02_Plan_Maestro'!$C$6:$C$285=A19)*'02_Plan_Maestro'!$P$6:$P$285*'02_Plan_Maestro'!$W$6:$W$285)/SUMIF('02_Plan_Maestro'!$C$6:$C$285,A19,'02_Plan_Maestro'!$P$6:$P$285),0) -> 0 | E19: =COUNTIFS('02_Plan_Maestro'!$C$6:$C$285,A19,'02_Plan_Maestro'!$R$6:$R$285,"<"&TODAY(),'02_Plan_Maestro'!$V$6:$V$285,"<>Completada") -> 0 | G19: Motor de transacciones | H19: =COUNTIF('02_Plan_Maestro'!$C$6:$C$285,G19) -> 0 | I19: =COUNTIFS('02_Plan_Maestro'!$C$6:$C$285,G19,'02_Plan_Maestro'!$V$6:$V$285,"Completada") -> 0 | J19: =IFERROR(SUMPRODUCT(('02_Plan_Maestro'!$C$6:$C$285=G19)*'02_Plan_Maestro'!$P$6:$P$285*'02_Plan_Maestro'!$W$6:$W$285)/SUMIF('02_Plan_Maestro'!$C$6:$C$285,G19,'02_Plan_Maestro'!$P$6:$P$285),0) -> 0
A20: Entidades | B20: =COUNTIF('02_Plan_Maestro'!$C$6:$C$285,A20) -> 0 | C20: =COUNTIFS('02_Plan_Maestro'!$C$6:$C$285,A20,'02_Plan_Maestro'!$V$6:$V$285,"Completada") -> 0 | D20: =IFERROR(SUMPRODUCT(('02_Plan_Maestro'!$C$6:$C$285=A20)*'02_Plan_Maestro'!$P$6:$P$285*'02_Plan_Maestro'!$W$6:$W$285)/SUMIF('02_Plan_Maestro'!$C$6:$C$285,A20,'02_Plan_Maestro'!$P$6:$P$285),0) -> 0 | E20: =COUNTIFS('02_Plan_Maestro'!$C$6:$C$285,A20,'02_Plan_Maestro'!$R$6:$R$285,"<"&TODAY(),'02_Plan_Maestro'!$V$6:$V$285,"<>Completada") -> 0 | G20: Ventas y Cuentas por Cobrar | H20: =COUNTIF('02_Plan_Maestro'!$C$6:$C$285,G20) -> 0 | I20: =COUNTIFS('02_Plan_Maestro'!$C$6:$C$285,G20,'02_Plan_Maestro'!$V$6:$V$285,"Completada") -> 0 | J20: =IFERROR(SUMPRODUCT(('02_Plan_Maestro'!$C$6:$C$285=G20)*'02_Plan_Maestro'!$P$6:$P$285*'02_Plan_Maestro'!$W$6:$W$285)/SUMIF('02_Plan_Maestro'!$C$6:$C$285,G20,'02_Plan_Maestro'!$P$6:$P$285),0) -> 0
A21: Compras y Cuentas por Pagar | B21: =COUNTIF('02_Plan_Maestro'!$C$6:$C$285,A21) -> 0 | C21: =COUNTIFS('02_Plan_Maestro'!$C$6:$C$285,A21,'02_Plan_Maestro'!$V$6:$V$285,"Completada") -> 0 | D21: =IFERROR(SUMPRODUCT(('02_Plan_Maestro'!$C$6:$C$285=A21)*'02_Plan_Maestro'!$P$6:$P$285*'02_Plan_Maestro'!$W$6:$W$285)/SUMIF('02_Plan_Maestro'!$C$6:$C$285,A21,'02_Plan_Maestro'!$P$6:$P$285),0) -> 0 | E21: =COUNTIFS('02_Plan_Maestro'!$C$6:$C$285,A21,'02_Plan_Maestro'!$R$6:$R$285,"<"&TODAY(),'02_Plan_Maestro'!$V$6:$V$285,"<>Completada") -> 0 | G21: Gastos | H21: =COUNTIF('02_Plan_Maestro'!$C$6:$C$285,G21) -> 0 | I21: =COUNTIFS('02_Plan_Maestro'!$C$6:$C$285,G21,'02_Plan_Maestro'!$V$6:$V$285,"Completada") -> 0 | J21: =IFERROR(SUMPRODUCT(('02_Plan_Maestro'!$C$6:$C$285=G21)*'02_Plan_Maestro'!$P$6:$P$285*'02_Plan_Maestro'!$W$6:$W$285)/SUMIF('02_Plan_Maestro'!$C$6:$C$285,G21,'02_Plan_Maestro'!$P$6:$P$285),0) -> 0
A22: Workflow y aprobaciones | B22: =COUNTIF('02_Plan_Maestro'!$C$6:$C$285,A22) -> 0 | C22: =COUNTIFS('02_Plan_Maestro'!$C$6:$C$285,A22,'02_Plan_Maestro'!$V$6:$V$285,"Completada") -> 0 | D22: =IFERROR(SUMPRODUCT(('02_Plan_Maestro'!$C$6:$C$285=A22)*'02_Plan_Maestro'!$P$6:$P$285*'02_Plan_Maestro'!$W$6:$W$285)/SUMIF('02_Plan_Maestro'!$C$6:$C$285,A22,'02_Plan_Maestro'!$P$6:$P$285),0) -> 0 | E22: =COUNTIFS('02_Plan_Maestro'!$C$6:$C$285,A22,'02_Plan_Maestro'!$R$6:$R$285,"<"&TODAY(),'02_Plan_Maestro'!$V$6:$V$285,"<>Completada") -> 0 | G22: Bancos | H22: =COUNTIF('02_Plan_Maestro'!$C$6:$C$285,G22) -> 0 | I22: =COUNTIFS('02_Plan_Maestro'!$C$6:$C$285,G22,'02_Plan_Maestro'!$V$6:$V$285,"Completada") -> 0 | J22: =IFERROR(SUMPRODUCT(('02_Plan_Maestro'!$C$6:$C$285=G22)*'02_Plan_Maestro'!$P$6:$P$285*'02_Plan_Maestro'!$W$6:$W$285)/SUMIF('02_Plan_Maestro'!$C$6:$C$285,G22,'02_Plan_Maestro'!$P$6:$P$285),0) -> 0
A23: Tesorería | B23: =COUNTIF('02_Plan_Maestro'!$C$6:$C$285,A23) -> 0 | C23: =COUNTIFS('02_Plan_Maestro'!$C$6:$C$285,A23,'02_Plan_Maestro'!$V$6:$V$285,"Completada") -> 0 | D23: =IFERROR(SUMPRODUCT(('02_Plan_Maestro'!$C$6:$C$285=A23)*'02_Plan_Maestro'!$P$6:$P$285*'02_Plan_Maestro'!$W$6:$W$285)/SUMIF('02_Plan_Maestro'!$C$6:$C$285,A23,'02_Plan_Maestro'!$P$6:$P$285),0) -> 0 | E23: =COUNTIFS('02_Plan_Maestro'!$C$6:$C$285,A23,'02_Plan_Maestro'!$R$6:$R$285,"<"&TODAY(),'02_Plan_Maestro'!$V$6:$V$285,"<>Completada") -> 0 | G23: Activos Fijos | H23: =COUNTIF('02_Plan_Maestro'!$C$6:$C$285,G23) -> 0 | I23: =COUNTIFS('02_Plan_Maestro'!$C$6:$C$285,G23,'02_Plan_Maestro'!$V$6:$V$285,"Completada") -> 0 | J23: =IFERROR(SUMPRODUCT(('02_Plan_Maestro'!$C$6:$C$285=G23)*'02_Plan_Maestro'!$P$6:$P$285*'02_Plan_Maestro'!$W$6:$W$285)/SUMIF('02_Plan_Maestro'!$C$6:$C$285,G23,'02_Plan_Maestro'!$P$6:$P$285),0) -> 0
A24: Inventario | B24: =COUNTIF('02_Plan_Maestro'!$C$6:$C$285,A24) -> 0 | C24: =COUNTIFS('02_Plan_Maestro'!$C$6:$C$285,A24,'02_Plan_Maestro'!$V$6:$V$285,"Completada") -> 0 | D24: =IFERROR(SUMPRODUCT(('02_Plan_Maestro'!$C$6:$C$285=A24)*'02_Plan_Maestro'!$P$6:$P$285*'02_Plan_Maestro'!$W$6:$W$285)/SUMIF('02_Plan_Maestro'!$C$6:$C$285,A24,'02_Plan_Maestro'!$P$6:$P$285),0) -> 0 | E24: =COUNTIFS('02_Plan_Maestro'!$C$6:$C$285,A24,'02_Plan_Maestro'!$R$6:$R$285,"<"&TODAY(),'02_Plan_Maestro'!$V$6:$V$285,"<>Completada") -> 0 | G24: Fiscal | H24: =COUNTIF('02_Plan_Maestro'!$C$6:$C$285,G24) -> 0 | I24: =COUNTIFS('02_Plan_Maestro'!$C$6:$C$285,G24,'02_Plan_Maestro'!$V$6:$V$285,"Completada") -> 0 | J24: =IFERROR(SUMPRODUCT(('02_Plan_Maestro'!$C$6:$C$285=G24)*'02_Plan_Maestro'!$P$6:$P$285*'02_Plan_Maestro'!$W$6:$W$285)/SUMIF('02_Plan_Maestro'!$C$6:$C$285,G24,'02_Plan_Maestro'!$P$6:$P$285),0) -> 0
A25: Intercompany y Consolidación | B25: =COUNTIF('02_Plan_Maestro'!$C$6:$C$285,A25) -> 0 | C25: =COUNTIFS('02_Plan_Maestro'!$C$6:$C$285,A25,'02_Plan_Maestro'!$V$6:$V$285,"Completada") -> 0 | D25: =IFERROR(SUMPRODUCT(('02_Plan_Maestro'!$C$6:$C$285=A25)*'02_Plan_Maestro'!$P$6:$P$285*'02_Plan_Maestro'!$W$6:$W$285)/SUMIF('02_Plan_Maestro'!$C$6:$C$285,A25,'02_Plan_Maestro'!$P$6:$P$285),0) -> 0 | E25: =COUNTIFS('02_Plan_Maestro'!$C$6:$C$285,A25,'02_Plan_Maestro'!$R$6:$R$285,"<"&TODAY(),'02_Plan_Maestro'!$V$6:$V$285,"<>Completada") -> 0 | G25: Documentos | H25: =COUNTIF('02_Plan_Maestro'!$C$6:$C$285,G25) -> 0 | I25: =COUNTIFS('02_Plan_Maestro'!$C$6:$C$285,G25,'02_Plan_Maestro'!$V$6:$V$285,"Completada") -> 0 | J25: =IFERROR(SUMPRODUCT(('02_Plan_Maestro'!$C$6:$C$285=G25)*'02_Plan_Maestro'!$P$6:$P$285*'02_Plan_Maestro'!$W$6:$W$285)/SUMIF('02_Plan_Maestro'!$C$6:$C$285,G25,'02_Plan_Maestro'!$P$6:$P$285),0) -> 0
A26: Auditoría | B26: =COUNTIF('02_Plan_Maestro'!$C$6:$C$285,A26) -> 0 | C26: =COUNTIFS('02_Plan_Maestro'!$C$6:$C$285,A26,'02_Plan_Maestro'!$V$6:$V$285,"Completada") -> 0 | D26: =IFERROR(SUMPRODUCT(('02_Plan_Maestro'!$C$6:$C$285=A26)*'02_Plan_Maestro'!$P$6:$P$285*'02_Plan_Maestro'!$W$6:$W$285)/SUMIF('02_Plan_Maestro'!$C$6:$C$285,A26,'02_Plan_Maestro'!$P$6:$P$285),0) -> 0 | E26: =COUNTIFS('02_Plan_Maestro'!$C$6:$C$285,A26,'02_Plan_Maestro'!$R$6:$R$285,"<"&TODAY(),'02_Plan_Maestro'!$V$6:$V$285,"<>Completada") -> 0 | G26: Informes | H26: =COUNTIF('02_Plan_Maestro'!$C$6:$C$285,G26) -> 0 | I26: =COUNTIFS('02_Plan_Maestro'!$C$6:$C$285,G26,'02_Plan_Maestro'!$V$6:$V$285,"Completada") -> 0 | J26: =IFERROR(SUMPRODUCT(('02_Plan_Maestro'!$C$6:$C$285=G26)*'02_Plan_Maestro'!$P$6:$P$285*'02_Plan_Maestro'!$W$6:$W$285)/SUMIF('02_Plan_Maestro'!$C$6:$C$285,G26,'02_Plan_Maestro'!$P$6:$P$285),0) -> 0
A27: IA (opcional) | B27: =COUNTIF('02_Plan_Maestro'!$C$6:$C$285,A27) -> 0 | C27: =COUNTIFS('02_Plan_Maestro'!$C$6:$C$285,A27,'02_Plan_Maestro'!$V$6:$V$285,"Completada") -> 0 | D27: =IFERROR(SUMPRODUCT(('02_Plan_Maestro'!$C$6:$C$285=A27)*'02_Plan_Maestro'!$P$6:$P$285*'02_Plan_Maestro'!$W$6:$W$285)/SUMIF('02_Plan_Maestro'!$C$6:$C$285,A27,'02_Plan_Maestro'!$P$6:$P$285),0) -> 0 | E27: =COUNTIFS('02_Plan_Maestro'!$C$6:$C$285,A27,'02_Plan_Maestro'!$R$6:$R$285,"<"&TODAY(),'02_Plan_Maestro'!$V$6:$V$285,"<>Completada") -> 0 | G27: Migración de datos | H27: =COUNTIF('02_Plan_Maestro'!$C$6:$C$285,G27) -> 0 | I27: =COUNTIFS('02_Plan_Maestro'!$C$6:$C$285,G27,'02_Plan_Maestro'!$V$6:$V$285,"Completada") -> 0 | J27: =IFERROR(SUMPRODUCT(('02_Plan_Maestro'!$C$6:$C$285=G27)*'02_Plan_Maestro'!$P$6:$P$285*'02_Plan_Maestro'!$W$6:$W$285)/SUMIF('02_Plan_Maestro'!$C$6:$C$285,G27,'02_Plan_Maestro'!$P$6:$P$285),0) -> 0
A28: Pruebas formación y salida | B28: =COUNTIF('02_Plan_Maestro'!$C$6:$C$285,A28) -> 0 | C28: =COUNTIFS('02_Plan_Maestro'!$C$6:$C$285,A28,'02_Plan_Maestro'!$V$6:$V$285,"Completada") -> 0 | D28: =IFERROR(SUMPRODUCT(('02_Plan_Maestro'!$C$6:$C$285=A28)*'02_Plan_Maestro'!$P$6:$P$285*'02_Plan_Maestro'!$W$6:$W$285)/SUMIF('02_Plan_Maestro'!$C$6:$C$285,A28,'02_Plan_Maestro'!$P$6:$P$285),0) -> 0 | E28: =COUNTIFS('02_Plan_Maestro'!$C$6:$C$285,A28,'02_Plan_Maestro'!$R$6:$R$285,"<"&TODAY(),'02_Plan_Maestro'!$V$6:$V$285,"<>Completada") -> 0

Sheet 02_Plan_Maestro
A1: PLAN MAESTRO DE IMPLEMENTACIÓN
A2: Actualice Estado y % avance. Duración y Semáforo son fórmulas.
A5: ID | B5: Fase | C5: Módulo | D5: Submódulo / proceso | E5: Actividad | F5: Detalle paso a paso | G5: Entregable | H5: Criterio de aceptación | I5: Evidencia requerida | J5: Alcance / filiales | K5: Responsable GENTIA | L5: Responsable cliente | M5: Predecesora | N5: Dependencia | O5: Prioridad | P5: Peso | Q5: Inicio plan | R5: Fin plan | S5: Duración hábil | T5: Inicio real | U5: Fin real | V5: Estado | W5: % avance | X5: Semáforo | Y5: Observaciones
A6: IMP-001 | B6: 1. Gobierno y preparación | C6: Gobierno del proyecto | D6: Acta de constitución y criterios de éxito | E6: Definir y aprobar: Acta de constitución y criterios de éxito | F6: 1) Convocar responsables de Acta de constitución y criterios de éxito. 2) Acordar alcance, fechas y dependencias. 3) Documentar decisión y responsable. 4) Obtener aprobación formal. 5) Archivar evidencia. | G6: Acta de constitución y criterios de éxito: configuración, evidencia y acta | H6: Acta de constitución y criterios de éxito documentado con responsable, fecha y aprobación formal. | I6: Capturas, archivo de prueba, conciliación y aprobación | J6: Todas las filiales / ajustar por ola | K6: Director de proyecto | L6: Patrocinador ejecutivo | N6: Prerrequisitos del módulo | O6: Alta | P6: 2 | Q6: 46328.75 | R6: 46331.75 | S6: =NETWORKDAYS(Q6,R6) -> 4 | V6: No iniciada | W6: 0 | X6: =IF(OR(V6="Completada",V6="No aplica"),"VERDE",IF(V6="Bloqueada","ROJO",IF(R6<TODAY(),"ROJO",IF(AND(R6-TODAY()<=7,W6<1),"AMARILLO","GRIS")))) -> GRIS
A7: IMP-002 | B7: 1. Gobierno y preparación | C7: Gobierno del proyecto | D7: Alcance por país, filial, módulo y proceso | E7: Definir y aprobar: Alcance por país, filial, módulo y proceso | F7: 1) Convocar responsables de Alcance por país, filial, módulo y proceso. 2) Acordar alcance, fechas y dependencias. 3) Documentar decisión y responsable. 4) Obtener aprobación formal. 5) Archivar evidencia. | G7: Alcance por país, filial, módulo y proceso: configuración, evidencia y acta | H7: Alcance por país, filial, módulo y proceso documentado con responsable, fecha y aprobación formal. | I7: Capturas, archivo de prueba, conciliación y aprobación | J7: Todas las filiales / ajustar por ola | K7: Director de proyecto | L7: Patrocinador ejecutivo | M7: IMP-001 | N7: Finalizar IMP-001 | O7: Alta | P7: 2 | Q7: 46332.75 | R7: 46336.75 | S7: =NETWORKDAYS(Q7,R7) -> 3 | V7: No iniciada | W7: 0 | X7: =IF(OR(V7="Completada",V7="No aplica"),"VERDE",IF(V7="Bloqueada","ROJO",IF(R7<TODAY(),"ROJO",IF(AND(R7-TODAY()<=7,W7<1),"AMARILLO","GRIS")))) -> GRIS
A8: IMP-003 | B8: 1. Gobierno y preparación | C8: Gobierno del proyecto | D8: Estrategia de rollout por olas | E8: Definir y aprobar: Estrategia de rollout por olas | F8: 1) Convocar responsables de Estrategia de rollout por olas. 2) Acordar alcance, fechas y dependencias. 3) Documentar decisión y responsable. 4) Obtener aprobación formal. 5) Archivar evidencia. | G8: Estrategia de rollout por olas: configuración, evidencia y acta | H8: Estrategia de rollout por olas documentado con responsable, fecha y aprobación formal. | I8: Capturas, archivo de prueba, conciliación y aprobación | J8: Todas las filiales / ajustar por ola | K8: Director de proyecto | L8: Patrocinador ejecutivo | M8: IMP-002 | N8: Finalizar IMP-002 | O8: Media | P8: 1 | Q8: 46337.75 | R8: 46339.75 | S8: =NETWORKDAYS(Q8,R8) -> 3 | V8: No iniciada | W8: 0 | X8: =IF(OR(V8="Completada",V8="No aplica"),"VERDE",IF(V8="Bloqueada","ROJO",IF(R8<TODAY(),"ROJO",IF(AND(R8-TODAY()<=7,W8<1),"AMARILLO","GRIS")))) -> GRIS
A9: IMP-004 | B9: 1. Gobierno y preparación | C9: Gobierno del proyecto | D9: RACI y disponibilidad de responsables | E9: Definir y aprobar: RACI y disponibilidad de responsables | F9: 1) Convocar responsables de RACI y disponibilidad de responsables. 2) Acordar alcance, fechas y dependencias. 3) Documentar decisión y responsable. 4) Obtener aprobación formal. 5) Archivar evidencia. | G9: RACI y disponibilidad de responsables: configuración, evidencia y acta | H9: RACI y disponibilidad de responsables documentado con responsable, fecha y aprobación formal. | I9: Capturas, archivo de prueba, conciliación y aprobación | J9: Todas las filiales / ajustar por ola | K9: Director de proyecto | L9: Patrocinador ejecutivo | M9: IMP-003 | N9: Finalizar IMP-003 | O9: Media | P9: 1 | Q9: 46342.75 | R9: 46345.75 | S9: =NETWORKDAYS(Q9,R9) -> 4 | V9: No iniciada | W9: 0 | X9: =IF(OR(V9="Completada",V9="No aplica"),"VERDE",IF(V9="Bloqueada","ROJO",IF(R9<TODAY(),"ROJO",IF(AND(R9-TODAY()<=7,W9<1),"AMARILLO","GRIS")))) -> GRIS
A10: IMP-005 | B10: 1. Gobierno y preparación | C10: Gobierno del proyecto | D10: Calendario de comités y comunicaciones | E10: Definir y aprobar: Calendario de comités y comunicaciones | F10: 1) Convocar responsables de Calendario de comités y comunicaciones. 2) Acordar alcance, fechas y dependencias. 3) Documentar decisión y responsable. 4) Obtener aprobación formal. 5) Archivar evidencia. | G10: Calendario de comités y comunicaciones: configuración, evidencia y acta | H10: Calendario de comités y comunicaciones documentado con responsable, fecha y aprobación formal. | I10: Capturas, archivo de prueba, conciliación y aprobación | J10: Todas las filiales / ajustar por ola | K10: Director de proyecto | L10: Patrocinador ejecutivo | M10: IMP-004 | N10: Finalizar IMP-004 | O10: Media | P10: 1 | Q10: 46346.75 | R10: 46350.75 | S10: =NETWORKDAYS(Q10,R10) -> 3 | V10: No iniciada | W10: 0 | X10: =IF(OR(V10="Completada",V10="No aplica"),"VERDE",IF(V10="Bloqueada","ROJO",IF(R10<TODAY(),"ROJO",IF(AND(R10-TODAY()<=7,W10<1),"AMARILLO","GRIS")))) -> GRIS
A11: IMP-006 | B11: 1. Gobierno y preparación | C11: Gobierno del proyecto | D11: Registro de riesgos, incidencias y decisiones | E11: Definir y aprobar: Registro de riesgos, incidencias y decisiones | F11: 1) Convocar responsables de Registro de riesgos, incidencias y decisiones. 2) Acordar alcance, fechas y dependencias. 3) Documentar decisión y responsable. 4) Obtener aprobación formal. 5) Archivar evidencia. | G11: Registro de riesgos, incidencias y decisiones: configuración, evidencia y acta | H11: Registro de riesgos, incidencias y decisiones documentado con responsable, fecha y aprobación formal. | I11: Capturas, archivo de prueba, conciliación y aprobación | J11: Todas las filiales / ajustar por ola | K11: Director de proyecto | L11: Patrocinador ejecutivo | M11: IMP-005 | N11: Finalizar IMP-005 | O11: Media | P11: 1 | Q11: 46351.75 | R11: 46353.75 | S11: =NETWORKDAYS(Q11,R11) -> 3 | V11: No iniciada | W11: 0 | X11: =IF(OR(V11="Completada",V11="No aplica"),"VERDE",IF(V11="Bloqueada","ROJO",IF(R11<TODAY(),"ROJO",IF(AND(R11-TODAY()<=7,W11<1),"AMARILLO","GRIS")))) -> GRIS
A12: IMP-007 | B12: 1. Gobierno y preparación | C12: Gobierno del proyecto | D12: Control de cambios de alcance | E12: Definir y aprobar: Control de cambios de alcance | F12: 1) Convocar responsables de Control de cambios de alcance. 2) Acordar alcance, fechas y dependencias. 3) Documentar decisión y responsable. 4) Obtener aprobación formal. 5) Archivar evidencia. | G12: Control de cambios de alcance: configuración, evidencia y acta | H12: Control de cambios de alcance documentado con responsable, fecha y aprobación formal. | I12: Capturas, archivo de prueba, conciliación y aprobación | J12: Todas las filiales / ajustar por ola | K12: Director de proyecto | L12: Patrocinador ejecutivo | M12: IMP-006 | N12: Finalizar IMP-006 | O12: Media | P12: 1 | Q12: 46356.75 | R12: 46359.75 | S12: =NETWORKDAYS(Q12,R12) -> 4 | V12: No iniciada | W12: 0 | X12: =IF(OR(V12="Completada",V12="No aplica"),"VERDE",IF(V12="Bloqueada","ROJO",IF(R12<TODAY(),"ROJO",IF(AND(R12-TODAY()<=7,W12<1),"AMARILLO","GRIS")))) -> GRIS
A13: IMP-008 | B13: 1. Gobierno y preparación | C13: Gobierno del proyecto | D13: Inventario de sistemas fuente e interfaces | E13: Definir y aprobar: Inventario de sistemas fuente e interfaces | F13: 1) Convocar responsables de Inventario de sistemas fuente e interfaces. 2) Acordar alcance, fechas y dependencias. 3) Documentar decisión y responsable. 4) Obtener aprobación formal. 5) Archivar evidencia. | G13: Inventario de sistemas fuente e interfaces: configuración, evidencia y acta | H13: Inventario de sistemas fuente e interfaces documentado con responsable, fecha y aprobación formal. | I13: Capturas, archivo de prueba, conciliación y aprobación | J13: Todas las filiales / ajustar por ola | K13: Director de proyecto | L13: Patrocinador ejecutivo | M13: IMP-007 | N13: Finalizar IMP-007 | O13: Media | P13: 1 | Q13: 46360.75 | R13: 46364.75 | S13: =NETWORKDAYS(Q13,R13) -> 3 | V13: No iniciada | W13: 0 | X13: =IF(OR(V13="Completada",V13="No aplica"),"VERDE",IF(V13="Bloqueada","ROJO",IF(R13<TODAY(),"ROJO",IF(AND(R13-TODAY()<=7,W13<1),"AMARILLO","GRIS")))) -> GRIS
A14: IMP-009 | B14: 1. Gobierno y preparación | C14: Gobierno del proyecto | D14: Plan de calidad y evidencias | E14: Definir y aprobar: Plan de calidad y evidencias | F14: 1) Convocar responsables de Plan de calidad y evidencias. 2) Acordar alcance, fechas y dependencias. 3) Documentar decisión y responsable. 4) Obtener aprobación formal. 5) Archivar evidencia. | G14: Plan de calidad y evidencias: configuración, evidencia y acta | H14: Plan de calidad y evidencias documentado con responsable, fecha y aprobación formal. | I14: Capturas, archivo de prueba, conciliación y aprobación | J14: Todas las filiales / ajustar por ola | K14: Director de proyecto | L14: Patrocinador ejecutivo | M14: IMP-008 | N14: Finalizar IMP-008 | O14: Media | P14: 1 | Q14: 46365.75 | R14: 46367.75 | S14: =NETWORKDAYS(Q14,R14) -> 3 | V14: No iniciada | W14: 0 | X14: =IF(OR(V14="Completada",V14="No aplica"),"VERDE",IF(V14="Bloqueada","ROJO",IF(R14<TODAY(),"ROJO",IF(AND(R14-TODAY()<=7,W14<1),"AMARILLO","GRIS")))) -> GRIS
A15: IMP-010 | B15: 1. Gobierno y preparación | C15: Infraestructura y plataforma | D15: Ambientes de desarrollo, pruebas y producción | E15: Configurar y validar: Ambientes de desarrollo, pruebas y producción | F15: 1) Diseñar Ambientes de desarrollo, pruebas y producción. 2) Configurar primero en pruebas sin exponer secretos. 3) Ejecutar prueba positiva, negativa y recuperación. 4) Documentar monitoreo y rollback. 5) Promover con aprobación. | G15: Ambientes de desarrollo, pruebas y producción: configuración, evidencia y acta | H15: Ambientes de desarrollo, pruebas y producción opera en pruebas y producción, sin secretos expuestos, con monitoreo y rollback verificado. | I15: Capturas, archivo de prueba, conciliación y aprobación | J15: Todas las filiales / ajustar por ola | K15: Líder técnico | L15: TI / Seguridad | N15: Prerrequisitos del módulo | O15: Crítica | P15: 3 | Q15: 46329.75 | R15: 46335.75 | S15: =NETWORKDAYS(Q15,R15) -> 5 | V15: No iniciada | W15: 0 | X15: =IF(OR(V15="Completada",V15="No aplica"),"VERDE",IF(V15="Bloqueada","ROJO",IF(R15<TODAY(),"ROJO",IF(AND(R15-TODAY()<=7,W15<1),"AMARILLO","GRIS")))) -> GRIS
A16: IMP-011 | B16: 1. Gobierno y preparación | C16: Infraestructura y plataforma | D16: Supabase, migraciones y políticas RLS | E16: Configurar y validar: Supabase, migraciones y políticas RLS | F16: 1) Diseñar Supabase, migraciones y políticas RLS. 2) Configurar primero en pruebas sin exponer secretos. 3) Ejecutar prueba positiva, negativa y recuperación. 4) Documentar monitoreo y rollback. 5) Promover con aprobación. | G16: Supabase, migraciones y políticas RLS: configuración, evidencia y acta | H16: Supabase, migraciones y políticas RLS opera en pruebas y producción, sin secretos expuestos, con monitoreo y rollback verificado. | I16: Capturas, archivo de prueba, conciliación y aprobación | J16: Todas las filiales / ajustar por ola | K16: Líder técnico | L16: TI / Seguridad | M16: IMP-010 | N16: Finalizar IMP-010 | O16: Crítica | P16: 3 | Q16: 46336.75 | R16: 46342.75 | S16: =NETWORKDAYS(Q16,R16) -> 5 | V16: No iniciada | W16: 0 | X16: =IF(OR(V16="Completada",V16="No aplica"),"VERDE",IF(V16="Bloqueada","ROJO",IF(R16<TODAY(),"ROJO",IF(AND(R16-TODAY()<=7,W16<1),"AMARILLO","GRIS")))) -> GRIS
A17: IMP-012 | B17: 1. Gobierno y preparación | C17: Infraestructura y plataforma | D17: Railway, variables protegidas y despliegue | E17: Configurar y validar: Railway, variables protegidas y despliegue | F17: 1) Diseñar Railway, variables protegidas y despliegue. 2) Configurar primero en pruebas sin exponer secretos. 3) Ejecutar prueba positiva, negativa y recuperación. 4) Documentar monitoreo y rollback. 5) Promover con aprobación. | G17: Railway, variables protegidas y despliegue: configuración, evidencia y acta | H17: Railway, variables protegidas y despliegue opera en pruebas y producción, sin secretos expuestos, con monitoreo y rollback verificado. | I17: Capturas, archivo de prueba, conciliación y aprobación | J17: Todas las filiales / ajustar por ola | K17: Líder técnico | L17: TI / Seguridad | M17: IMP-011 | N17: Finalizar IMP-011 | O17: Media | P17: 1 | Q17: 46343.75 | R17: 46345.75 | S17: =NETWORKDAYS(Q17,R17) -> 3 | V17: No iniciada | W17: 0 | X17: =IF(OR(V17="Completada",V17="No aplica"),"VERDE",IF(V17="Bloqueada","ROJO",IF(R17<TODAY(),"ROJO",IF(AND(R17-TODAY()<=7,W17<1),"AMARILLO","GRIS")))) -> GRIS
A18: IMP-013 | B18: 1. Gobierno y preparación | C18: Infraestructura y plataforma | D18: Dominio HTTPS, Cloudflare y Turnstile | E18: Configurar y validar: Dominio HTTPS, Cloudflare y Turnstile | F18: 1) Diseñar Dominio HTTPS, Cloudflare y Turnstile. 2) Configurar primero en pruebas sin exponer secretos. 3) Ejecutar prueba positiva, negativa y recuperación. 4) Documentar monitoreo y rollback. 5) Promover con aprobación. | G18: Dominio HTTPS, Cloudflare y Turnstile: configuración, evidencia y acta | H18: Dominio HTTPS, Cloudflare y Turnstile opera en pruebas y producción, sin secretos expuestos, con monitoreo y rollback verificado. | I18: Capturas, archivo de prueba, conciliación y aprobación | J18: Todas las filiales / ajustar por ola | K18: Líder técnico | L18: TI / Seguridad | M18: IMP-012 | N18: Finalizar IMP-012 | O18: Media | P18: 1 | Q18: 46346.75 | R18: 46351.75 | S18: =NETWORKDAYS(Q18,R18) -> 4 | V18: No iniciada | W18: 0 | X18: =IF(OR(V18="Completada",V18="No aplica"),"VERDE",IF(V18="Bloqueada","ROJO",IF(R18<TODAY(),"ROJO",IF(AND(R18-TODAY()<=7,W18<1),"AMARILLO","GRIS")))) -> GRIS
A19: IMP-014 | B19: 1. Gobierno y preparación | C19: Infraestructura y plataforma | D19: SMTP y correo transaccional | E19: Configurar y validar: SMTP y correo transaccional | F19: 1) Diseñar SMTP y correo transaccional. 2) Configurar primero en pruebas sin exponer secretos. 3) Ejecutar prueba positiva, negativa y recuperación. 4) Documentar monitoreo y rollback. 5) Promover con aprobación. | G19: SMTP y correo transaccional: configuración, evidencia y acta | H19: SMTP y correo transaccional opera en pruebas y producción, sin secretos expuestos, con monitoreo y rollback verificado. | I19: Capturas, archivo de prueba, conciliación y aprobación | J19: Todas las filiales / ajustar por ola | K19: Líder técnico | L19: TI / Seguridad | M19: IMP-013 | N19: Finalizar IMP-013 | O19: Media | P19: 1 | Q19: 46352.75 | R19: 46356.75 | S19: =NETWORKDAYS(Q19,R19) -> 3 | V19: No iniciada | W19: 0 | X19: =IF(OR(V19="Completada",V19="No aplica"),"VERDE",IF(V19="Bloqueada","ROJO",IF(R19<TODAY(),"ROJO",IF(AND(R19-TODAY()<=7,W19<1),"AMARILLO","GRIS")))) -> GRIS
A20: IMP-015 | B20: 1. Gobierno y preparación | C20: Infraestructura y plataforma | D20: URLs de autenticación y recuperación | E20: Configurar y validar: URLs de autenticación y recuperación | F20: 1) Diseñar URLs de autenticación y recuperación. 2) Configurar primero en pruebas sin exponer secretos. 3) Ejecutar prueba positiva, negativa y recuperación. 4) Documentar monitoreo y rollback. 5) Promover con aprobación. | G20: URLs de autenticación y recuperación: configuración, evidencia y acta | H20: URLs de autenticación y recuperación opera en pruebas y producción, sin secretos expuestos, con monitoreo y rollback verificado. | I20: Capturas, archivo de prueba, conciliación y aprobación | J20: Todas las filiales / ajustar por ola | K20: Líder técnico | L20: TI / Seguridad | M20: IMP-014 | N20: Finalizar IMP-014 | O20: Crítica | P20: 3 | Q20: 46357.75 | R20: 46363.75 | S20: =NETWORKDAYS(Q20,R20) -> 5 | V20: No iniciada | W20: 0 | X20: =IF(OR(V20="Completada",V20="No aplica"),"VERDE",IF(V20="Bloqueada","ROJO",IF(R20<TODAY(),"ROJO",IF(AND(R20-TODAY()<=7,W20<1),"AMARILLO","GRIS")))) -> GRIS
A21: IMP-016 | B21: 1. Gobierno y preparación | C21: Infraestructura y plataforma | D21: Respaldos y restauración | E21: Configurar y validar: Respaldos y restauración | F21: 1) Diseñar Respaldos y restauración. 2) Configurar primero en pruebas sin exponer secretos. 3) Ejecutar prueba positiva, negativa y recuperación. 4) Documentar monitoreo y rollback. 5) Promover con aprobación. | G21: Respaldos y restauración: configuración, evidencia y acta | H21: Respaldos y restauración opera en pruebas y producción, sin secretos expuestos, con monitoreo y rollback verificado. | I21: Capturas, archivo de prueba, conciliación y aprobación | J21: Todas las filiales / ajustar por ola | K21: Líder técnico | L21: TI / Seguridad | M21: IMP-015 | N21: Finalizar IMP-015 | O21: Media | P21: 1 | Q21: 46364.75 | R21: 46367.75 | S21: =NETWORKDAYS(Q21,R21) -> 4 | V21: No iniciada | W21: 0 | X21: =IF(OR(V21="Completada",V21="No aplica"),"VERDE",IF(V21="Bloqueada","ROJO",IF(R21<TODAY(),"ROJO",IF(AND(R21-TODAY()<=7,W21<1),"AMARILLO","GRIS")))) -> GRIS
A22: IMP-017 | B22: 1. Gobierno y preparación | C22: Infraestructura y plataforma | D22: Monitoreo, logs y alertas | E22: Configurar y validar: Monitoreo, logs y alertas | F22: 1) Diseñar Monitoreo, logs y alertas. 2) Configurar primero en pruebas sin exponer secretos. 3) Ejecutar prueba positiva, negativa y recuperación. 4) Documentar monitoreo y rollback. 5) Promover con aprobación. | G22: Monitoreo, logs y alertas: configuración, evidencia y acta | H22: Monitoreo, logs y alertas opera en pruebas y producción, sin secretos expuestos, con monitoreo y rollback verificado. | I22: Capturas, archivo de prueba, conciliación y aprobación | J22: Todas las filiales / ajustar por ola | K22: Líder técnico | L22: TI / Seguridad | M22: IMP-016 | N22: Finalizar IMP-016 | O22: Media | P22: 1 | Q22: 46370.75 | R22: 46372.75 | S22: =NETWORKDAYS(Q22,R22) -> 3 | V22: No iniciada | W22: 0 | X22: =IF(OR(V22="Completada",V22="No aplica"),"VERDE",IF(V22="Bloqueada","ROJO",IF(R22<TODAY(),"ROJO",IF(AND(R22-TODAY()<=7,W22<1),"AMARILLO","GRIS")))) -> GRIS
A23: IMP-018 | B23: 1. Gobierno y preparación | C23: Infraestructura y plataforma | D23: Procedimiento de despliegue y rollback | E23: Configurar y validar: Procedimiento de despliegue y rollback | F23: 1) Diseñar Procedimiento de despliegue y rollback. 2) Configurar primero en pruebas sin exponer secretos. 3) Ejecutar prueba positiva, negativa y recuperación. 4) Documentar monitoreo y rollback. 5) Promover con aprobación. | G23: Procedimiento de despliegue y rollback: configuración, evidencia y acta | H23: Procedimiento de despliegue y rollback opera en pruebas y producción, sin secretos expuestos, con monitoreo y rollback verificado. | I23: Capturas, archivo de prueba, conciliación y aprobación | J23: Todas las filiales / ajustar por ola | K23: Líder técnico | L23: TI / Seguridad | M23: IMP-017 | N23: Finalizar IMP-017 | O23: Media | P23: 1 | Q23: 46373.75 | R23: 46377.75 | S23: =NETWORKDAYS(Q23,R23) -> 3 | V23: No iniciada | W23: 0 | X23: =IF(OR(V23="Completada",V23="No aplica"),"VERDE",IF(V23="Bloqueada","ROJO",IF(R23<TODAY(),"ROJO",IF(AND(R23-TODAY()<=7,W23<1),"AMARILLO","GRIS")))) -> GRIS
A24: IMP-019 | B24: 2. Fundamentos y diseño | C24: CORE | D24: Países e identificadores ISO | E24: Configurar y validar: Países e identificadores ISO | F24: 1) Levantar política para Países e identificadores ISO. 2) Preparar datos. 3) Parametrizar por filial. 4) Probar escenario normal, excepción y multimoneda cuando aplique. 5) Conciliar impacto y aprobar. | G24: Países e identificadores ISO: configuración, evidencia y acta | H24: Países e identificadores ISO funciona de extremo a extremo y contabiliza correctamente. | I24: Capturas, archivo de prueba, conciliación y aprobación | J24: Todas las filiales / ajustar por ola | K24: Líder funcional GENTIA | L24: Dueño de datos | N24: Prerrequisitos del módulo | O24: Alta | P24: 2 | Q24: 46344.75 | R24: 46349.75 | S24: =NETWORKDAYS(Q24,R24) -> 4 | V24: No iniciada | W24: 0 | X24: =IF(OR(V24="Completada",V24="No aplica"),"VERDE",IF(V24="Bloqueada","ROJO",IF(R24<TODAY(),"ROJO",IF(AND(R24-TODAY()<=7,W24<1),"AMARILLO","GRIS")))) -> GRIS
A25: IMP-020 | B25: 2. Fundamentos y diseño | C25: CORE | D25: Idiomas y zonas horarias | E25: Configurar y validar: Idiomas y zonas horarias | F25: 1) Levantar política para Idiomas y zonas horarias. 2) Preparar datos. 3) Parametrizar por filial. 4) Probar escenario normal, excepción y multimoneda cuando aplique. 5) Conciliar impacto y aprobar. | G25: Idiomas y zonas horarias: configuración, evidencia y acta | H25: Idiomas y zonas horarias funciona de extremo a extremo y contabiliza correctamente. | I25: Capturas, archivo de prueba, conciliación y aprobación | J25: Todas las filiales / ajustar por ola | K25: Líder funcional GENTIA | L25: Dueño de datos | M25: IMP-019 | N25: Finalizar IMP-019 | O25: Alta | P25: 2 | Q25: 46350.75 | R25: 46352.75 | S25: =NETWORKDAYS(Q25,R25) -> 3 | V25: No iniciada | W25: 0 | X25: =IF(OR(V25="Completada",V25="No aplica"),"VERDE",IF(V25="Bloqueada","ROJO",IF(R25<TODAY(),"ROJO",IF(AND(R25-TODAY()<=7,W25<1),"AMARILLO","GRIS")))) -> GRIS
A26: IMP-021 | B26: 2. Fundamentos y diseño | C26: CORE | D26: Monedas y precisión cambiaria | E26: Configurar y validar: Monedas y precisión cambiaria | F26: 1) Levantar política para Monedas y precisión cambiaria. 2) Preparar datos. 3) Parametrizar por filial. 4) Probar escenario normal, excepción y multimoneda cuando aplique. 5) Conciliar impacto y aprobar. | G26: Monedas y precisión cambiaria: configuración, evidencia y acta | H26: Monedas y precisión cambiaria funciona de extremo a extremo y contabiliza correctamente. | I26: Capturas, archivo de prueba, conciliación y aprobación | J26: Todas las filiales / ajustar por ola | K26: Líder funcional GENTIA | L26: Dueño de datos | M26: IMP-020 | N26: Finalizar IMP-020 | O26: Media | P26: 1 | Q26: 46353.75 | R26: 46357.75 | S26: =NETWORKDAYS(Q26,R26) -> 3 | V26: No iniciada | W26: 0 | X26: =IF(OR(V26="Completada",V26="No aplica"),"VERDE",IF(V26="Bloqueada","ROJO",IF(R26<TODAY(),"ROJO",IF(AND(R26-TODAY()<=7,W26<1),"AMARILLO","GRIS")))) -> GRIS
A27: IMP-022 | B27: 2. Fundamentos y diseño | C27: CORE | D27: Estados maestros | E27: Configurar y validar: Estados maestros | F27: 1) Levantar política para Estados maestros. 2) Preparar datos. 3) Parametrizar por filial. 4) Probar escenario normal, excepción y multimoneda cuando aplique. 5) Conciliar impacto y aprobar. | G27: Estados maestros: configuración, evidencia y acta | H27: Estados maestros funciona de extremo a extremo y contabiliza correctamente. | I27: Capturas, archivo de prueba, conciliación y aprobación | J27: Todas las filiales / ajustar por ola | K27: Líder funcional GENTIA | L27: Dueño de datos | M27: IMP-021 | N27: Finalizar IMP-021 | O27: Media | P27: 1 | Q27: 46358.75 | R27: 46363.75 | S27: =NETWORKDAYS(Q27,R27) -> 4 | V27: No iniciada | W27: 0 | X27: =IF(OR(V27="Completada",V27="No aplica"),"VERDE",IF(V27="Bloqueada","ROJO",IF(R27<TODAY(),"ROJO",IF(AND(R27-TODAY()<=7,W27<1),"AMARILLO","GRIS")))) -> GRIS
A28: IMP-023 | B28: 2. Fundamentos y diseño | C28: CORE | D28: Tipos de transacción | E28: Configurar y validar: Tipos de transacción | F28: 1) Levantar política para Tipos de transacción. 2) Preparar datos. 3) Parametrizar por filial. 4) Probar escenario normal, excepción y multimoneda cuando aplique. 5) Conciliar impacto y aprobar. | G28: Tipos de transacción: configuración, evidencia y acta | H28: Tipos de transacción funciona de extremo a extremo y contabiliza correctamente. | I28: Capturas, archivo de prueba, conciliación y aprobación | J28: Todas las filiales / ajustar por ola | K28: Líder funcional GENTIA | L28: Dueño de datos | M28: IMP-022 | N28: Finalizar IMP-022 | O28: Media | P28: 1 | Q28: 46364.75 | R28: 46366.75 | S28: =NETWORKDAYS(Q28,R28) -> 3 | V28: No iniciada | W28: 0 | X28: =IF(OR(V28="Completada",V28="No aplica"),"VERDE",IF(V28="Bloqueada","ROJO",IF(R28<TODAY(),"ROJO",IF(AND(R28-TODAY()<=7,W28<1),"AMARILLO","GRIS")))) -> GRIS
A29: IMP-024 | B29: 2. Fundamentos y diseño | C29: CORE | D29: Secuencias por filial y transacción | E29: Configurar y validar: Secuencias por filial y transacción | F29: 1) Levantar política para Secuencias por filial y transacción. 2) Preparar datos. 3) Parametrizar por filial. 4) Probar escenario normal, excepción y multimoneda cuando aplique. 5) Conciliar impacto y aprobar. | G29: Secuencias por filial y transacción: configuración, evidencia y acta | H29: Secuencias por filial y transacción funciona de extremo a extremo y contabiliza correctamente. | I29: Capturas, archivo de prueba, conciliación y aprobación | J29: Todas las filiales / ajustar por ola | K29: Líder funcional GENTIA | L29: Dueño de datos | M29: IMP-023 | N29: Finalizar IMP-023 | O29: Media | P29: 1 | Q29: 46367.75 | R29: 46371.75 | S29: =NETWORKDAYS(Q29,R29) -> 3 | V29: No iniciada | W29: 0 | X29: =IF(OR(V29="Completada",V29="No aplica"),"VERDE",IF(V29="Bloqueada","ROJO",IF(R29<TODAY(),"ROJO",IF(AND(R29-TODAY()<=7,W29<1),"AMARILLO","GRIS")))) -> GRIS
A30: IMP-025 | B30: 2. Fundamentos y diseño | C30: CORE | D30: Prefijos, longitud y consecutivo inicial | E30: Configurar y validar: Prefijos, longitud y consecutivo inicial | F30: 1) Levantar política para Prefijos, longitud y consecutivo inicial. 2) Preparar datos. 3) Parametrizar por filial. 4) Probar escenario normal, excepción y multimoneda cuando aplique. 5) Conciliar impacto y aprobar. | G30: Prefijos, longitud y consecutivo inicial: configuración, evidencia y acta | H30: Prefijos, longitud y consecutivo inicial funciona de extremo a extremo y contabiliza correctamente. | I30: Capturas, archivo de prueba, conciliación y aprobación | J30: Todas las filiales / ajustar por ola | K30: Líder funcional GENTIA | L30: Dueño de datos | M30: IMP-024 | N30: Finalizar IMP-024 | O30: Media | P30: 1 | Q30: 46372.75 | R30: 46377.75 | S30: =NETWORKDAYS(Q30,R30) -> 4 | V30: No iniciada | W30: 0 | X30: =IF(OR(V30="Completada",V30="No aplica"),"VERDE",IF(V30="Bloqueada","ROJO",IF(R30<TODAY(),"ROJO",IF(AND(R30-TODAY()<=7,W30<1),"AMARILLO","GRIS")))) -> GRIS
A31: IMP-026 | B31: 2. Fundamentos y diseño | C31: CORE | D31: Parámetros globales | E31: Configurar y validar: Parámetros globales | F31: 1) Levantar política para Parámetros globales. 2) Preparar datos. 3) Parametrizar por filial. 4) Probar escenario normal, excepción y multimoneda cuando aplique. 5) Conciliar impacto y aprobar. | G31: Parámetros globales: configuración, evidencia y acta | H31: Parámetros globales funciona de extremo a extremo y contabiliza correctamente. | I31: Capturas, archivo de prueba, conciliación y aprobación | J31: Todas las filiales / ajustar por ola | K31: Líder funcional GENTIA | L31: Dueño de datos | M31: IMP-025 | N31: Finalizar IMP-025 | O31: Media | P31: 1 | Q31: 46378.75 | R31: 46380.75 | S31: =NETWORKDAYS(Q31,R31) -> 3 | V31: No iniciada | W31: 0 | X31: =IF(OR(V31="Completada",V31="No aplica"),"VERDE",IF(V31="Bloqueada","ROJO",IF(R31<TODAY(),"ROJO",IF(AND(R31-TODAY()<=7,W31<1),"AMARILLO","GRIS")))) -> GRIS
A32: IMP-027 | B32: 2. Fundamentos y diseño | C32: CORE | D32: Configuraciones por alcance | E32: Configurar y validar: Configuraciones por alcance | F32: 1) Levantar política para Configuraciones por alcance. 2) Preparar datos. 3) Parametrizar por filial. 4) Probar escenario normal, excepción y multimoneda cuando aplique. 5) Conciliar impacto y aprobar. | G32: Configuraciones por alcance: configuración, evidencia y acta | H32: Configuraciones por alcance funciona de extremo a extremo y contabiliza correctamente. | I32: Capturas, archivo de prueba, conciliación y aprobación | J32: Todas las filiales / ajustar por ola | K32: Líder funcional GENTIA | L32: Dueño de datos | M32: IMP-026 | N32: Finalizar IMP-026 | O32: Media | P32: 1 | Q32: 46381.75 | R32: 46385.75 | S32: =NETWORKDAYS(Q32,R32) -> 3 | V32: No iniciada | W32: 0 | X32: =IF(OR(V32="Completada",V32="No aplica"),"VERDE",IF(V32="Bloqueada","ROJO",IF(R32<TODAY(),"ROJO",IF(AND(R32-TODAY()<=7,W32<1),"AMARILLO","GRIS")))) -> GRIS
A33: IMP-028 | B33: 2. Fundamentos y diseño | C33: Organización | D33: Jerarquía de subsidiarias | E33: Configurar y validar: Jerarquía de subsidiarias | F33: 1) Levantar política para Jerarquía de subsidiarias. 2) Preparar datos. 3) Parametrizar por filial. 4) Probar escenario normal, excepción y multimoneda cuando aplique. 5) Conciliar impacto y aprobar. | G33: Jerarquía de subsidiarias: configuración, evidencia y acta | H33: Jerarquía de subsidiarias funciona de extremo a extremo y contabiliza correctamente. | I33: Capturas, archivo de prueba, conciliación y aprobación | J33: Todas las filiales / ajustar por ola | K33: Consultor funcional | L33: Contabilidad corporativa | N33: Prerrequisitos del módulo | O33: Alta | P33: 2 | Q33: 46345.75 | R33: 46350.75 | S33: =NETWORKDAYS(Q33,R33) -> 4 | V33: No iniciada | W33: 0 | X33: =IF(OR(V33="Completada",V33="No aplica"),"VERDE",IF(V33="Bloqueada","ROJO",IF(R33<TODAY(),"ROJO",IF(AND(R33-TODAY()<=7,W33<1),"AMARILLO","GRIS")))) -> GRIS
A34: IMP-029 | B34: 2. Fundamentos y diseño | C34: Organización | D34: Años y calendarios fiscales | E34: Configurar y validar: Años y calendarios fiscales | F34: 1) Levantar política para Años y calendarios fiscales. 2) Preparar datos. 3) Parametrizar por filial. 4) Probar escenario normal, excepción y multimoneda cuando aplique. 5) Conciliar impacto y aprobar. | G34: Años y calendarios fiscales: configuración, evidencia y acta | H34: Años y calendarios fiscales funciona de extremo a extremo y contabiliza correctamente. | I34: Capturas, archivo de prueba, conciliación y aprobación | J34: Todas las filiales / ajustar por ola | K34: Consultor funcional | L34: Contabilidad corporativa | M34: IMP-028 | N34: Finalizar IMP-028 | O34: Alta | P34: 2 | Q34: 46351.75 | R34: 46353.75 | S34: =NETWORKDAYS(Q34,R34) -> 3 | V34: No iniciada | W34: 0 | X34: =IF(OR(V34="Completada",V34="No aplica"),"VERDE",IF(V34="Bloqueada","ROJO",IF(R34<TODAY(),"ROJO",IF(AND(R34-TODAY()<=7,W34<1),"AMARILLO","GRIS")))) -> GRIS
A35: IMP-030 | B35: 2. Fundamentos y diseño | C35: Organización | D35: Períodos contables | E35: Configurar y validar: Períodos contables | F35: 1) Levantar política para Períodos contables. 2) Preparar datos. 3) Parametrizar por filial. 4) Probar escenario normal, excepción y multimoneda cuando aplique. 5) Conciliar impacto y aprobar. | G35: Períodos contables: configuración, evidencia y acta | H35: Períodos contables funciona de extremo a extremo y contabiliza correctamente. | I35: Capturas, archivo de prueba, conciliación y aprobación | J35: Todas las filiales / ajustar por ola | K35: Consultor funcional | L35: Contabilidad corporativa | M35: IMP-029 | N35: Finalizar IMP-029 | O35: Media | P35: 1 | Q35: 46356.75 | R35: 46358.75 | S35: =NETWORKDAYS(Q35,R35) -> 3 | V35: No iniciada | W35: 0 | X35: =IF(OR(V35="Completada",V35="No aplica"),"VERDE",IF(V35="Bloqueada","ROJO",IF(R35<TODAY(),"ROJO",IF(AND(R35-TODAY()<=7,W35<1),"AMARILLO","GRIS")))) -> GRIS
A36: IMP-031 | B36: 2. Fundamentos y diseño | C36: Organización | D36: Moneda funcional y zona horaria por filial | E36: Configurar y validar: Moneda funcional y zona horaria por filial | F36: 1) Levantar política para Moneda funcional y zona horaria por filial. 2) Preparar datos. 3) Parametrizar por filial. 4) Probar escenario normal, excepción y multimoneda cuando aplique. 5) Conciliar impacto y aprobar. | G36: Moneda funcional y zona horaria por filial: configuración, evidencia y acta | H36: Moneda funcional y zona horaria por filial funciona de extremo a extremo y contabiliza correctamente. | I36: Capturas, archivo de prueba, conciliación y aprobación | J36: Todas las filiales / ajustar por ola | K36: Consultor funcional | L36: Contabilidad corporativa | M36: IMP-030 | N36: Finalizar IMP-030 | O36: Media | P36: 1 | Q36: 46359.75 | R36: 46364.75 | S36: =NETWORKDAYS(Q36,R36) -> 4 | V36: No iniciada | W36: 0 | X36: =IF(OR(V36="Completada",V36="No aplica"),"VERDE",IF(V36="Bloqueada","ROJO",IF(R36<TODAY(),"ROJO",IF(AND(R36-TODAY()<=7,W36<1),"AMARILLO","GRIS")))) -> GRIS
A37: IMP-032 | B37: 2. Fundamentos y diseño | C37: Organización | D37: Sucursales y ubicaciones | E37: Configurar y validar: Sucursales y ubicaciones | F37: 1) Levantar política para Sucursales y ubicaciones. 2) Preparar datos. 3) Parametrizar por filial. 4) Probar escenario normal, excepción y multimoneda cuando aplique. 5) Conciliar impacto y aprobar. | G37: Sucursales y ubicaciones: configuración, evidencia y acta | H37: Sucursales y ubicaciones funciona de extremo a extremo y contabiliza correctamente. | I37: Capturas, archivo de prueba, conciliación y aprobación | J37: Todas las filiales / ajustar por ola | K37: Consultor funcional | L37: Contabilidad corporativa | M37: IMP-031 | N37: Finalizar IMP-031 | O37: Media | P37: 1 | Q37: 46365.75 | R37: 46367.75 | S37: =NETWORKDAYS(Q37,R37) -> 3 | V37: No iniciada | W37: 0 | X37: =IF(OR(V37="Completada",V37="No aplica"),"VERDE",IF(V37="Bloqueada","ROJO",IF(R37<TODAY(),"ROJO",IF(AND(R37-TODAY()<=7,W37<1),"AMARILLO","GRIS")))) -> GRIS
A38: IMP-033 | B38: 2. Fundamentos y diseño | C38: Organización | D38: Tipos de departamento Cliente e Interno | E38: Configurar y validar: Tipos de departamento Cliente e Interno | F38: 1) Levantar política para Tipos de departamento Cliente e Interno. 2) Preparar datos. 3) Parametrizar por filial. 4) Probar escenario normal, excepción y multimoneda cuando aplique. 5) Conciliar impacto y aprobar. | G38: Tipos de departamento Cliente e Interno: configuración, evidencia y acta | H38: Tipos de departamento Cliente e Interno funciona de extremo a extremo y contabiliza correctamente. | I38: Capturas, archivo de prueba, conciliación y aprobación | J38: Todas las filiales / ajustar por ola | K38: Consultor funcional | L38: Contabilidad corporativa | M38: IMP-032 | N38: Finalizar IMP-032 | O38: Media | P38: 1 | Q38: 46370.75 | R38: 46372.75 | S38: =NETWORKDAYS(Q38,R38) -> 3 | V38: No iniciada | W38: 0 | X38: =IF(OR(V38="Completada",V38="No aplica"),"VERDE",IF(V38="Bloqueada","ROJO",IF(R38<TODAY(),"ROJO",IF(AND(R38-TODAY()<=7,W38<1),"AMARILLO","GRIS")))) -> GRIS
A39: IMP-034 | B39: 2. Fundamentos y diseño | C39: Organización | D39: Departamentos y jerarquía | E39: Configurar y validar: Departamentos y jerarquía | F39: 1) Levantar política para Departamentos y jerarquía. 2) Preparar datos. 3) Parametrizar por filial. 4) Probar escenario normal, excepción y multimoneda cuando aplique. 5) Conciliar impacto y aprobar. | G39: Departamentos y jerarquía: configuración, evidencia y acta | H39: Departamentos y jerarquía funciona de extremo a extremo y contabiliza correctamente. | I39: Capturas, archivo de prueba, conciliación y aprobación | J39: Todas las filiales / ajustar por ola | K39: Consultor funcional | L39: Contabilidad corporativa | M39: IMP-033 | N39: Finalizar IMP-033 | O39: Media | P39: 1 | Q39: 46373.75 | R39: 46378.75 | S39: =NETWORKDAYS(Q39,R39) -> 4 | V39: No iniciada | W39: 0 | X39: =IF(OR(V39="Completada",V39="No aplica"),"VERDE",IF(V39="Bloqueada","ROJO",IF(R39<TODAY(),"ROJO",IF(AND(R39-TODAY()<=7,W39<1),"AMARILLO","GRIS")))) -> GRIS
A40: IMP-035 | B40: 2. Fundamentos y diseño | C40: Organización | D40: Clases analíticas | E40: Configurar y validar: Clases analíticas | F40: 1) Levantar política para Clases analíticas. 2) Preparar datos. 3) Parametrizar por filial. 4) Probar escenario normal, excepción y multimoneda cuando aplique. 5) Conciliar impacto y aprobar. | G40: Clases analíticas: configuración, evidencia y acta | H40: Clases analíticas funciona de extremo a extremo y contabiliza correctamente. | I40: Capturas, archivo de prueba, conciliación y aprobación | J40: Todas las filiales / ajustar por ola | K40: Consultor funcional | L40: Contabilidad corporativa | M40: IMP-034 | N40: Finalizar IMP-034 | O40: Media | P40: 1 | Q40: 46379.75 | R40: 46381.75 | S40: =NETWORKDAYS(Q40,R40) -> 3 | V40: No iniciada | W40: 0 | X40: =IF(OR(V40="Completada",V40="No aplica"),"VERDE",IF(V40="Bloqueada","ROJO",IF(R40<TODAY(),"ROJO",IF(AND(R40-TODAY()<=7,W40<1),"AMARILLO","GRIS")))) -> GRIS
A41: IMP-036 | B41: 2. Fundamentos y diseño | C41: Organización | D41: Centros de costos | E41: Configurar y validar: Centros de costos | F41: 1) Levantar política para Centros de costos. 2) Preparar datos. 3) Parametrizar por filial. 4) Probar escenario normal, excepción y multimoneda cuando aplique. 5) Conciliar impacto y aprobar. | G41: Centros de costos: configuración, evidencia y acta | H41: Centros de costos funciona de extremo a extremo y contabiliza correctamente. | I41: Capturas, archivo de prueba, conciliación y aprobación | J41: Todas las filiales / ajustar por ola | K41: Consultor funcional | L41: Contabilidad corporativa | M41: IMP-035 | N41: Finalizar IMP-035 | O41: Media | P41: 1 | Q41: 46384.75 | R41: 46386.75 | S41: =NETWORKDAYS(Q41,R41) -> 3 | V41: No iniciada | W41: 0 | X41: =IF(OR(V41="Completada",V41="No aplica"),"VERDE",IF(V41="Bloqueada","ROJO",IF(R41<TODAY(),"ROJO",IF(AND(R41-TODAY()<=7,W41<1),"AMARILLO","GRIS")))) -> GRIS
A42: IMP-037 | B42: 2. Fundamentos y diseño | C42: Organización | D42: Acreedores financieros | E42: Configurar y validar: Acreedores financieros | F42: 1) Levantar política para Acreedores financieros. 2) Preparar datos. 3) Parametrizar por filial. 4) Probar escenario normal, excepción y multimoneda cuando aplique. 5) Conciliar impacto y aprobar. | G42: Acreedores financieros: configuración, evidencia y acta | H42: Acreedores financieros funciona de extremo a extremo y contabiliza correctamente. | I42: Capturas, archivo de prueba, conciliación y aprobación | J42: Todas las filiales / ajustar por ola | K42: Consultor funcional | L42: Contabilidad corporativa | M42: IMP-036 | N42: Finalizar IMP-036 | O42: Media | P42: 1 | Q42: 46387.75 | R42: 46392.75 | S42: =NETWORKDAYS(Q42,R42) -> 4 | V42: No iniciada | W42: 0 | X42: =IF(OR(V42="Completada",V42="No aplica"),"VERDE",IF(V42="Bloqueada","ROJO",IF(R42<TODAY(),"ROJO",IF(AND(R42-TODAY()<=7,W42<1),"AMARILLO","GRIS")))) -> GRIS
A43: IMP-038 | B43: 2. Fundamentos y diseño | C43: Organización | D43: Compañías relacionadas | E43: Configurar y validar: Compañías relacionadas | F43: 1) Levantar política para Compañías relacionadas. 2) Preparar datos. 3) Parametrizar por filial. 4) Probar escenario normal, excepción y multimoneda cuando aplique. 5) Conciliar impacto y aprobar. | G43: Compañías relacionadas: configuración, evidencia y acta | H43: Compañías relacionadas funciona de extremo a extremo y contabiliza correctamente. | I43: Capturas, archivo de prueba, conciliación y aprobación | J43: Todas las filiales / ajustar por ola | K43: Consultor funcional | L43: Contabilidad corporativa | M43: IMP-037 | N43: Finalizar IMP-037 | O43: Media | P43: 1 | Q43: 46393.75 | R43: 46395.75 | S43: =NETWORKDAYS(Q43,R43) -> 3 | V43: No iniciada | W43: 0 | X43: =IF(OR(V43="Completada",V43="No aplica"),"VERDE",IF(V43="Bloqueada","ROJO",IF(R43<TODAY(),"ROJO",IF(AND(R43-TODAY()<=7,W43<1),"AMARILLO","GRIS")))) -> GRIS
A44: IMP-039 | B44: 2. Fundamentos y diseño | C44: Organización | D44: Aprobadores por filial | E44: Configurar y validar: Aprobadores por filial | F44: 1) Levantar política para Aprobadores por filial. 2) Preparar datos. 3) Parametrizar por filial. 4) Probar escenario normal, excepción y multimoneda cuando aplique. 5) Conciliar impacto y aprobar. | G44: Aprobadores por filial: configuración, evidencia y acta | H44: Aprobadores por filial funciona de extremo a extremo y contabiliza correctamente. | I44: Capturas, archivo de prueba, conciliación y aprobación | J44: Todas las filiales / ajustar por ola | K44: Consultor funcional | L44: Contabilidad corporativa | M44: IMP-038 | N44: Finalizar IMP-038 | O44: Media | P44: 1 | Q44: 46398.75 | R44: 46400.75 | S44: =NETWORKDAYS(Q44,R44) -> 3 | V44: No iniciada | W44: 0 | X44: =IF(OR(V44="Completada",V44="No aplica"),"VERDE",IF(V44="Bloqueada","ROJO",IF(R44<TODAY(),"ROJO",IF(AND(R44-TODAY()<=7,W44<1),"AMARILLO","GRIS")))) -> GRIS
A45: IMP-040 | B45: 2. Fundamentos y diseño | C45: Organización | D45: Obligatoriedad de dimensiones | E45: Configurar y validar: Obligatoriedad de dimensiones | F45: 1) Levantar política para Obligatoriedad de dimensiones. 2) Preparar datos. 3) Parametrizar por filial. 4) Probar escenario normal, excepción y multimoneda cuando aplique. 5) Conciliar impacto y aprobar. | G45: Obligatoriedad de dimensiones: configuración, evidencia y acta | H45: Obligatoriedad de dimensiones funciona de extremo a extremo y contabiliza correctamente. | I45: Capturas, archivo de prueba, conciliación y aprobación | J45: Todas las filiales / ajustar por ola | K45: Consultor funcional | L45: Contabilidad corporativa | M45: IMP-039 | N45: Finalizar IMP-039 | O45: Media | P45: 1 | Q45: 46401.75 | R45: 46406.75 | S45: =NETWORKDAYS(Q45,R45) -> 4 | V45: No iniciada | W45: 0 | X45: =IF(OR(V45="Completada",V45="No aplica"),"VERDE",IF(V45="Bloqueada","ROJO",IF(R45<TODAY(),"ROJO",IF(AND(R45-TODAY()<=7,W45<1),"AMARILLO","GRIS")))) -> GRIS
A46: IMP-041 | B46: 2. Fundamentos y diseño | C46: Seguridad | D46: Usuarios e invitación segura | E46: Configurar y validar: Usuarios e invitación segura | F46: 1) Definir regla y responsables de Usuarios e invitación segura. 2) Configurar permisos, trazabilidad y excepciones. 3) Probar caso autorizado y no autorizado. 4) Revisar bitácora. 5) Obtener conformidad de Control Interno. | G46: Usuarios e invitación segura: configuración, evidencia y acta | H46: Usuarios e invitación segura permite solo acciones autorizadas y registra actor, fecha y resultado. | I46: Capturas, archivo de prueba, conciliación y aprobación | J46: Todas las filiales / ajustar por ola | K46: Administrador de seguridad | L46: TI / Auditoría | N46: Prerrequisitos del módulo | O46: Alta | P46: 2 | Q46: 46346.75 | R46: 46351.75 | S46: =NETWORKDAYS(Q46,R46) -> 4 | V46: No iniciada | W46: 0 | X46: =IF(OR(V46="Completada",V46="No aplica"),"VERDE",IF(V46="Bloqueada","ROJO",IF(R46<TODAY(),"ROJO",IF(AND(R46-TODAY()<=7,W46<1),"AMARILLO","GRIS")))) -> GRIS
A47: IMP-042 | B47: 2. Fundamentos y diseño | C47: Seguridad | D47: Roles corporativos y locales | E47: Configurar y validar: Roles corporativos y locales | F47: 1) Definir regla y responsables de Roles corporativos y locales. 2) Configurar permisos, trazabilidad y excepciones. 3) Probar caso autorizado y no autorizado. 4) Revisar bitácora. 5) Obtener conformidad de Control Interno. | G47: Roles corporativos y locales: configuración, evidencia y acta | H47: Roles corporativos y locales permite solo acciones autorizadas y registra actor, fecha y resultado. | I47: Capturas, archivo de prueba, conciliación y aprobación | J47: Todas las filiales / ajustar por ola | K47: Administrador de seguridad | L47: TI / Auditoría | M47: IMP-041 | N47: Finalizar IMP-041 | O47: Alta | P47: 2 | Q47: 46352.75 | R47: 46356.75 | S47: =NETWORKDAYS(Q47,R47) -> 3 | V47: No iniciada | W47: 0 | X47: =IF(OR(V47="Completada",V47="No aplica"),"VERDE",IF(V47="Bloqueada","ROJO",IF(R47<TODAY(),"ROJO",IF(AND(R47-TODAY()<=7,W47<1),"AMARILLO","GRIS")))) -> GRIS
A48: IMP-043 | B48: 2. Fundamentos y diseño | C48: Seguridad | D48: Permisos Ver Crear Editar Eliminar | E48: Configurar y validar: Permisos Ver Crear Editar Eliminar | F48: 1) Definir regla y responsables de Permisos Ver Crear Editar Eliminar. 2) Configurar permisos, trazabilidad y excepciones. 3) Probar caso autorizado y no autorizado. 4) Revisar bitácora. 5) Obtener conformidad de Control Interno. | G48: Permisos Ver Crear Editar Eliminar: configuración, evidencia y acta | H48: Permisos Ver Crear Editar Eliminar permite solo acciones autorizadas y registra actor, fecha y resultado. | I48: Capturas, archivo de prueba, conciliación y aprobación | J48: Todas las filiales / ajustar por ola | K48: Administrador de seguridad | L48: TI / Auditoría | M48: IMP-042 | N48: Finalizar IMP-042 | O48: Alta | P48: 2 | Q48: 46357.75 | R48: 46359.75 | S48: =NETWORKDAYS(Q48,R48) -> 3 | V48: No iniciada | W48: 0 | X48: =IF(OR(V48="Completada",V48="No aplica"),"VERDE",IF(V48="Bloqueada","ROJO",IF(R48<TODAY(),"ROJO",IF(AND(R48-TODAY()<=7,W48<1),"AMARILLO","GRIS")))) -> GRIS
A49: IMP-044 | B49: 2. Fundamentos y diseño | C49: Seguridad | D49: Roles por usuario | E49: Configurar y validar: Roles por usuario | F49: 1) Definir regla y responsables de Roles por usuario. 2) Configurar permisos, trazabilidad y excepciones. 3) Probar caso autorizado y no autorizado. 4) Revisar bitácora. 5) Obtener conformidad de Control Interno. | G49: Roles por usuario: configuración, evidencia y acta | H49: Roles por usuario permite solo acciones autorizadas y registra actor, fecha y resultado. | I49: Capturas, archivo de prueba, conciliación y aprobación | J49: Todas las filiales / ajustar por ola | K49: Administrador de seguridad | L49: TI / Auditoría | M49: IMP-043 | N49: Finalizar IMP-043 | O49: Media | P49: 1 | Q49: 46360.75 | R49: 46365.75 | S49: =NETWORKDAYS(Q49,R49) -> 4 | V49: No iniciada | W49: 0 | X49: =IF(OR(V49="Completada",V49="No aplica"),"VERDE",IF(V49="Bloqueada","ROJO",IF(R49<TODAY(),"ROJO",IF(AND(R49-TODAY()<=7,W49<1),"AMARILLO","GRIS")))) -> GRIS
A50: IMP-045 | B50: 2. Fundamentos y diseño | C50: Seguridad | D50: Empresas por usuario | E50: Configurar y validar: Empresas por usuario | F50: 1) Definir regla y responsables de Empresas por usuario. 2) Configurar permisos, trazabilidad y excepciones. 3) Probar caso autorizado y no autorizado. 4) Revisar bitácora. 5) Obtener conformidad de Control Interno. | G50: Empresas por usuario: configuración, evidencia y acta | H50: Empresas por usuario permite solo acciones autorizadas y registra actor, fecha y resultado. | I50: Capturas, archivo de prueba, conciliación y aprobación | J50: Todas las filiales / ajustar por ola | K50: Administrador de seguridad | L50: TI / Auditoría | M50: IMP-044 | N50: Finalizar IMP-044 | O50: Media | P50: 1 | Q50: 46366.75 | R50: 46370.75 | S50: =NETWORKDAYS(Q50,R50) -> 3 | V50: No iniciada | W50: 0 | X50: =IF(OR(V50="Completada",V50="No aplica"),"VERDE",IF(V50="Bloqueada","ROJO",IF(R50<TODAY(),"ROJO",IF(AND(R50-TODAY()<=7,W50<1),"AMARILLO","GRIS")))) -> GRIS
A51: IMP-046 | B51: 2. Fundamentos y diseño | C51: Seguridad | D51: Segregación de funciones | E51: Configurar y validar: Segregación de funciones | F51: 1) Definir regla y responsables de Segregación de funciones. 2) Configurar permisos, trazabilidad y excepciones. 3) Probar caso autorizado y no autorizado. 4) Revisar bitácora. 5) Obtener conformidad de Control Interno. | G51: Segregación de funciones: configuración, evidencia y acta | H51: Segregación de funciones permite solo acciones autorizadas y registra actor, fecha y resultado. | I51: Capturas, archivo de prueba, conciliación y aprobación | J51: Todas las filiales / ajustar por ola | K51: Administrador de seguridad | L51: TI / Auditoría | M51: IMP-045 | N51: Finalizar IMP-045 | O51: Media | P51: 1 | Q51: 46371.75 | R51: 46373.75 | S51: =NETWORKDAYS(Q51,R51) -> 3 | V51: No iniciada | W51: 0 | X51: =IF(OR(V51="Completada",V51="No aplica"),"VERDE",IF(V51="Bloqueada","ROJO",IF(R51<TODAY(),"ROJO",IF(AND(R51-TODAY()<=7,W51<1),"AMARILLO","GRIS")))) -> GRIS
A52: IMP-047 | B52: 2. Fundamentos y diseño | C52: Seguridad | D52: Cambio y recuperación de contraseña | E52: Configurar y validar: Cambio y recuperación de contraseña | F52: 1) Definir regla y responsables de Cambio y recuperación de contraseña. 2) Configurar permisos, trazabilidad y excepciones. 3) Probar caso autorizado y no autorizado. 4) Revisar bitácora. 5) Obtener conformidad de Control Interno. | G52: Cambio y recuperación de contraseña: configuración, evidencia y acta | H52: Cambio y recuperación de contraseña permite solo acciones autorizadas y registra actor, fecha y resultado. | I52: Capturas, archivo de prueba, conciliación y aprobación | J52: Todas las filiales / ajustar por ola | K52: Administrador de seguridad | L52: TI / Auditoría | M52: IMP-046 | N52: Finalizar IMP-046 | O52: Media | P52: 1 | Q52: 46374.75 | R52: 46379.75 | S52: =NETWORKDAYS(Q52,R52) -> 4 | V52: No iniciada | W52: 0 | X52: =IF(OR(V52="Completada",V52="No aplica"),"VERDE",IF(V52="Bloqueada","ROJO",IF(R52<TODAY(),"ROJO",IF(AND(R52-TODAY()<=7,W52<1),"AMARILLO","GRIS")))) -> GRIS
A53: IMP-048 | B53: 2. Fundamentos y diseño | C53: Seguridad | D53: Sesiones y dispositivos | E53: Configurar y validar: Sesiones y dispositivos | F53: 1) Definir regla y responsables de Sesiones y dispositivos. 2) Configurar permisos, trazabilidad y excepciones. 3) Probar caso autorizado y no autorizado. 4) Revisar bitácora. 5) Obtener conformidad de Control Interno. | G53: Sesiones y dispositivos: configuración, evidencia y acta | H53: Sesiones y dispositivos permite solo acciones autorizadas y registra actor, fecha y resultado. | I53: Capturas, archivo de prueba, conciliación y aprobación | J53: Todas las filiales / ajustar por ola | K53: Administrador de seguridad | L53: TI / Auditoría | M53: IMP-047 | N53: Finalizar IMP-047 | O53: Media | P53: 1 | Q53: 46380.75 | R53: 46384.75 | S53: =NETWORKDAYS(Q53,R53) -> 3 | V53: No iniciada | W53: 0 | X53: =IF(OR(V53="Completada",V53="No aplica"),"VERDE",IF(V53="Bloqueada","ROJO",IF(R53<TODAY(),"ROJO",IF(AND(R53-TODAY()<=7,W53<1),"AMARILLO","GRIS")))) -> GRIS
A54: IMP-049 | B54: 2. Fundamentos y diseño | C54: Seguridad | D54: Historial de acceso | E54: Configurar y validar: Historial de acceso | F54: 1) Definir regla y responsables de Historial de acceso. 2) Configurar permisos, trazabilidad y excepciones. 3) Probar caso autorizado y no autorizado. 4) Revisar bitácora. 5) Obtener conformidad de Control Interno. | G54: Historial de acceso: configuración, evidencia y acta | H54: Historial de acceso permite solo acciones autorizadas y registra actor, fecha y resultado. | I54: Capturas, archivo de prueba, conciliación y aprobación | J54: Todas las filiales / ajustar por ola | K54: Administrador de seguridad | L54: TI / Auditoría | M54: IMP-048 | N54: Finalizar IMP-048 | O54: Media | P54: 1 | Q54: 46385.75 | R54: 46387.75 | S54: =NETWORKDAYS(Q54,R54) -> 3 | V54: No iniciada | W54: 0 | X54: =IF(OR(V54="Completada",V54="No aplica"),"VERDE",IF(V54="Bloqueada","ROJO",IF(R54<TODAY(),"ROJO",IF(AND(R54-TODAY()<=7,W54<1),"AMARILLO","GRIS")))) -> GRIS
A55: IMP-050 | B55: 2. Fundamentos y diseño | C55: Seguridad | D55: Menús y permisos | E55: Configurar y validar: Menús y permisos | F55: 1) Definir regla y responsables de Menús y permisos. 2) Configurar permisos, trazabilidad y excepciones. 3) Probar caso autorizado y no autorizado. 4) Revisar bitácora. 5) Obtener conformidad de Control Interno. | G55: Menús y permisos: configuración, evidencia y acta | H55: Menús y permisos permite solo acciones autorizadas y registra actor, fecha y resultado. | I55: Capturas, archivo de prueba, conciliación y aprobación | J55: Todas las filiales / ajustar por ola | K55: Administrador de seguridad | L55: TI / Auditoría | M55: IMP-049 | N55: Finalizar IMP-049 | O55: Alta | P55: 2 | Q55: 46388.75 | R55: 46393.75 | S55: =NETWORKDAYS(Q55,R55) -> 4 | V55: No iniciada | W55: 0 | X55: =IF(OR(V55="Completada",V55="No aplica"),"VERDE",IF(V55="Bloqueada","ROJO",IF(R55<TODAY(),"ROJO",IF(AND(R55-TODAY()<=7,W55<1),"AMARILLO","GRIS")))) -> GRIS
A56: IMP-051 | B56: 3. Configuración funcional | C56: Configuración transversal | D56: Términos de pago | E56: Configurar y validar: Términos de pago | F56: 1) Levantar política para Términos de pago. 2) Preparar datos. 3) Parametrizar por filial. 4) Probar escenario normal, excepción y multimoneda cuando aplique. 5) Conciliar impacto y aprobar. | G56: Términos de pago: configuración, evidencia y acta | H56: Términos de pago funciona de extremo a extremo y contabiliza correctamente. | I56: Capturas, archivo de prueba, conciliación y aprobación | J56: Todas las filiales / ajustar por ola | K56: Consultor funcional | L56: Contabilidad / Impuestos | N56: Prerrequisitos del módulo | O56: Alta | P56: 2 | Q56: 46363.75 | R56: 46366.75 | S56: =NETWORKDAYS(Q56,R56) -> 4 | V56: No iniciada | W56: 0 | X56: =IF(OR(V56="Completada",V56="No aplica"),"VERDE",IF(V56="Bloqueada","ROJO",IF(R56<TODAY(),"ROJO",IF(AND(R56-TODAY()<=7,W56<1),"AMARILLO","GRIS")))) -> GRIS
A57: IMP-052 | B57: 3. Configuración funcional | C57: Configuración transversal | D57: Métodos de pago | E57: Configurar y validar: Métodos de pago | F57: 1) Levantar política para Métodos de pago. 2) Preparar datos. 3) Parametrizar por filial. 4) Probar escenario normal, excepción y multimoneda cuando aplique. 5) Conciliar impacto y aprobar. | G57: Métodos de pago: configuración, evidencia y acta | H57: Métodos de pago funciona de extremo a extremo y contabiliza correctamente. | I57: Capturas, archivo de prueba, conciliación y aprobación | J57: Todas las filiales / ajustar por ola | K57: Consultor funcional | L57: Contabilidad / Impuestos | M57: IMP-051 | N57: Finalizar IMP-051 | O57: Alta | P57: 2 | Q57: 46367.75 | R57: 46371.75 | S57: =NETWORKDAYS(Q57,R57) -> 3 | V57: No iniciada | W57: 0 | X57: =IF(OR(V57="Completada",V57="No aplica"),"VERDE",IF(V57="Bloqueada","ROJO",IF(R57<TODAY(),"ROJO",IF(AND(R57-TODAY()<=7,W57<1),"AMARILLO","GRIS")))) -> GRIS
A58: IMP-053 | B58: 3. Configuración funcional | C58: Configuración transversal | D58: Unidades de medida | E58: Configurar y validar: Unidades de medida | F58: 1) Levantar política para Unidades de medida. 2) Preparar datos. 3) Parametrizar por filial. 4) Probar escenario normal, excepción y multimoneda cuando aplique. 5) Conciliar impacto y aprobar. | G58: Unidades de medida: configuración, evidencia y acta | H58: Unidades de medida funciona de extremo a extremo y contabiliza correctamente. | I58: Capturas, archivo de prueba, conciliación y aprobación | J58: Todas las filiales / ajustar por ola | K58: Consultor funcional | L58: Contabilidad / Impuestos | M58: IMP-052 | N58: Finalizar IMP-052 | O58: Media | P58: 1 | Q58: 46372.75 | R58: 46374.75 | S58: =NETWORKDAYS(Q58,R58) -> 3 | V58: No iniciada | W58: 0 | X58: =IF(OR(V58="Completada",V58="No aplica"),"VERDE",IF(V58="Bloqueada","ROJO",IF(R58<TODAY(),"ROJO",IF(AND(R58-TODAY()<=7,W58<1),"AMARILLO","GRIS")))) -> GRIS
A59: IMP-054 | B59: 3. Configuración funcional | C59: Configuración transversal | D59: Tipos, códigos y grupos de impuestos | E59: Configurar y validar: Tipos, códigos y grupos de impuestos | F59: 1) Levantar política para Tipos, códigos y grupos de impuestos. 2) Preparar datos. 3) Parametrizar por filial. 4) Probar escenario normal, excepción y multimoneda cuando aplique. 5) Conciliar impacto y aprobar. | G59: Tipos, códigos y grupos de impuestos: configuración, evidencia y acta | H59: Tipos, códigos y grupos de impuestos funciona de extremo a extremo y contabiliza correctamente. | I59: Capturas, archivo de prueba, conciliación y aprobación | J59: Todas las filiales / ajustar por ola | K59: Consultor funcional | L59: Contabilidad / Impuestos | M59: IMP-053 | N59: Finalizar IMP-053 | O59: Alta | P59: 2 | Q59: 46377.75 | R59: 46380.75 | S59: =NETWORKDAYS(Q59,R59) -> 4 | V59: No iniciada | W59: 0 | X59: =IF(OR(V59="Completada",V59="No aplica"),"VERDE",IF(V59="Bloqueada","ROJO",IF(R59<TODAY(),"ROJO",IF(AND(R59-TODAY()<=7,W59<1),"AMARILLO","GRIS")))) -> GRIS
A60: IMP-055 | B60: 3. Configuración funcional | C60: Configuración transversal | D60: Retenciones y autorretenciones | E60: Configurar y validar: Retenciones y autorretenciones | F60: 1) Levantar política para Retenciones y autorretenciones. 2) Preparar datos. 3) Parametrizar por filial. 4) Probar escenario normal, excepción y multimoneda cuando aplique. 5) Conciliar impacto y aprobar. | G60: Retenciones y autorretenciones: configuración, evidencia y acta | H60: Retenciones y autorretenciones funciona de extremo a extremo y contabiliza correctamente. | I60: Capturas, archivo de prueba, conciliación y aprobación | J60: Todas las filiales / ajustar por ola | K60: Consultor funcional | L60: Contabilidad / Impuestos | M60: IMP-054 | N60: Finalizar IMP-054 | O60: Media | P60: 1 | Q60: 46381.75 | R60: 46385.75 | S60: =NETWORKDAYS(Q60,R60) -> 3 | V60: No iniciada | W60: 0 | X60: =IF(OR(V60="Completada",V60="No aplica"),"VERDE",IF(V60="Bloqueada","ROJO",IF(R60<TODAY(),"ROJO",IF(AND(R60-TODAY()<=7,W60<1),"AMARILLO","GRIS")))) -> GRIS
A61: IMP-056 | B61: 3. Configuración funcional | C61: Configuración transversal | D61: Agencias tributarias por filial | E61: Configurar y validar: Agencias tributarias por filial | F61: 1) Levantar política para Agencias tributarias por filial. 2) Preparar datos. 3) Parametrizar por filial. 4) Probar escenario normal, excepción y multimoneda cuando aplique. 5) Conciliar impacto y aprobar. | G61: Agencias tributarias por filial: configuración, evidencia y acta | H61: Agencias tributarias por filial funciona de extremo a extremo y contabiliza correctamente. | I61: Capturas, archivo de prueba, conciliación y aprobación | J61: Todas las filiales / ajustar por ola | K61: Consultor funcional | L61: Contabilidad / Impuestos | M61: IMP-055 | N61: Finalizar IMP-055 | O61: Media | P61: 1 | Q61: 46386.75 | R61: 46388.75 | S61: =NETWORKDAYS(Q61,R61) -> 3 | V61: No iniciada | W61: 0 | X61: =IF(OR(V61="Completada",V61="No aplica"),"VERDE",IF(V61="Bloqueada","ROJO",IF(R61<TODAY(),"ROJO",IF(AND(R61-TODAY()<=7,W61<1),"AMARILLO","GRIS")))) -> GRIS
A62: IMP-057 | B62: 3. Configuración funcional | C62: Configuración transversal | D62: Series y tipos documentales | E62: Configurar y validar: Series y tipos documentales | F62: 1) Levantar política para Series y tipos documentales. 2) Preparar datos. 3) Parametrizar por filial. 4) Probar escenario normal, excepción y multimoneda cuando aplique. 5) Conciliar impacto y aprobar. | G62: Series y tipos documentales: configuración, evidencia y acta | H62: Series y tipos documentales funciona de extremo a extremo y contabiliza correctamente. | I62: Capturas, archivo de prueba, conciliación y aprobación | J62: Todas las filiales / ajustar por ola | K62: Consultor funcional | L62: Contabilidad / Impuestos | M62: IMP-056 | N62: Finalizar IMP-056 | O62: Media | P62: 1 | Q62: 46391.75 | R62: 46394.75 | S62: =NETWORKDAYS(Q62,R62) -> 4 | V62: No iniciada | W62: 0 | X62: =IF(OR(V62="Completada",V62="No aplica"),"VERDE",IF(V62="Bloqueada","ROJO",IF(R62<TODAY(),"ROJO",IF(AND(R62-TODAY()<=7,W62<1),"AMARILLO","GRIS")))) -> GRIS
A63: IMP-058 | B63: 3. Configuración funcional | C63: Configuración transversal | D63: Días feriados | E63: Configurar y validar: Días feriados | F63: 1) Levantar política para Días feriados. 2) Preparar datos. 3) Parametrizar por filial. 4) Probar escenario normal, excepción y multimoneda cuando aplique. 5) Conciliar impacto y aprobar. | G63: Días feriados: configuración, evidencia y acta | H63: Días feriados funciona de extremo a extremo y contabiliza correctamente. | I63: Capturas, archivo de prueba, conciliación y aprobación | J63: Todas las filiales / ajustar por ola | K63: Consultor funcional | L63: Contabilidad / Impuestos | M63: IMP-057 | N63: Finalizar IMP-057 | O63: Media | P63: 1 | Q63: 46395.75 | R63: 46399.75 | S63: =NETWORKDAYS(Q63,R63) -> 3 | V63: No iniciada | W63: 0 | X63: =IF(OR(V63="Completada",V63="No aplica"),"VERDE",IF(V63="Bloqueada","ROJO",IF(R63<TODAY(),"ROJO",IF(AND(R63-TODAY()<=7,W63<1),"AMARILLO","GRIS")))) -> GRIS
A64: IMP-059 | B64: 3. Configuración funcional | C64: Configuración transversal | D64: Tipos de cambio diarios | E64: Configurar y validar: Tipos de cambio diarios | F64: 1) Levantar política para Tipos de cambio diarios. 2) Preparar datos. 3) Parametrizar por filial. 4) Probar escenario normal, excepción y multimoneda cuando aplique. 5) Conciliar impacto y aprobar. | G64: Tipos de cambio diarios: configuración, evidencia y acta | H64: Tipos de cambio diarios funciona de extremo a extremo y contabiliza correctamente. | I64: Capturas, archivo de prueba, conciliación y aprobación | J64: Todas las filiales / ajustar por ola | K64: Consultor funcional | L64: Contabilidad / Impuestos | M64: IMP-058 | N64: Finalizar IMP-058 | O64: Media | P64: 1 | Q64: 46400.75 | R64: 46402.75 | S64: =NETWORKDAYS(Q64,R64) -> 3 | V64: No iniciada | W64: 0 | X64: =IF(OR(V64="Completada",V64="No aplica"),"VERDE",IF(V64="Bloqueada","ROJO",IF(R64<TODAY(),"ROJO",IF(AND(R64-TODAY()<=7,W64<1),"AMARILLO","GRIS")))) -> GRIS
A65: IMP-060 | B65: 3. Configuración funcional | C65: Configuración transversal | D65: Tasas consolidadas | E65: Configurar y validar: Tasas consolidadas | F65: 1) Levantar política para Tasas consolidadas. 2) Preparar datos. 3) Parametrizar por filial. 4) Probar escenario normal, excepción y multimoneda cuando aplique. 5) Conciliar impacto y aprobar. | G65: Tasas consolidadas: configuración, evidencia y acta | H65: Tasas consolidadas funciona de extremo a extremo y contabiliza correctamente. | I65: Capturas, archivo de prueba, conciliación y aprobación | J65: Todas las filiales / ajustar por ola | K65: Consultor funcional | L65: Contabilidad / Impuestos | M65: IMP-059 | N65: Finalizar IMP-059 | O65: Media | P65: 1 | Q65: 46405.75 | R65: 46408.75 | S65: =NETWORKDAYS(Q65,R65) -> 4 | V65: No iniciada | W65: 0 | X65: =IF(OR(V65="Completada",V65="No aplica"),"VERDE",IF(V65="Bloqueada","ROJO",IF(R65<TODAY(),"ROJO",IF(AND(R65-TODAY()<=7,W65<1),"AMARILLO","GRIS")))) -> GRIS
A66: IMP-061 | B66: 3. Configuración funcional | C66: Configuración transversal | D66: Fuentes y tolerancias de tasa | E66: Configurar y validar: Fuentes y tolerancias de tasa | F66: 1) Levantar política para Fuentes y tolerancias de tasa. 2) Preparar datos. 3) Parametrizar por filial. 4) Probar escenario normal, excepción y multimoneda cuando aplique. 5) Conciliar impacto y aprobar. | G66: Fuentes y tolerancias de tasa: configuración, evidencia y acta | H66: Fuentes y tolerancias de tasa funciona de extremo a extremo y contabiliza correctamente. | I66: Capturas, archivo de prueba, conciliación y aprobación | J66: Todas las filiales / ajustar por ola | K66: Consultor funcional | L66: Contabilidad / Impuestos | M66: IMP-060 | N66: Finalizar IMP-060 | O66: Media | P66: 1 | Q66: 46409.75 | R66: 46413.75 | S66: =NETWORKDAYS(Q66,R66) -> 3 | V66: No iniciada | W66: 0 | X66: =IF(OR(V66="Completada",V66="No aplica"),"VERDE",IF(V66="Bloqueada","ROJO",IF(R66<TODAY(),"ROJO",IF(AND(R66-TODAY()<=7,W66<1),"AMARILLO","GRIS")))) -> GRIS
A67: IMP-062 | B67: 3. Configuración funcional | C67: Configuración transversal | D67: Plantillas de notificación | E67: Configurar y validar: Plantillas de notificación | F67: 1) Levantar política para Plantillas de notificación. 2) Preparar datos. 3) Parametrizar por filial. 4) Probar escenario normal, excepción y multimoneda cuando aplique. 5) Conciliar impacto y aprobar. | G67: Plantillas de notificación: configuración, evidencia y acta | H67: Plantillas de notificación funciona de extremo a extremo y contabiliza correctamente. | I67: Capturas, archivo de prueba, conciliación y aprobación | J67: Todas las filiales / ajustar por ola | K67: Consultor funcional | L67: Contabilidad / Impuestos | M67: IMP-061 | N67: Finalizar IMP-061 | O67: Media | P67: 1 | Q67: 46414.75 | R67: 46416.75 | S67: =NETWORKDAYS(Q67,R67) -> 3 | V67: No iniciada | W67: 0 | X67: =IF(OR(V67="Completada",V67="No aplica"),"VERDE",IF(V67="Bloqueada","ROJO",IF(R67<TODAY(),"ROJO",IF(AND(R67-TODAY()<=7,W67<1),"AMARILLO","GRIS")))) -> GRIS
A68: IMP-063 | B68: 3. Configuración funcional | C68: Configuración transversal | D68: Mantenimiento de aprobadores UP | E68: Configurar y validar: Mantenimiento de aprobadores UP | F68: 1) Levantar política para Mantenimiento de aprobadores UP. 2) Preparar datos. 3) Parametrizar por filial. 4) Probar escenario normal, excepción y multimoneda cuando aplique. 5) Conciliar impacto y aprobar. | G68: Mantenimiento de aprobadores UP: configuración, evidencia y acta | H68: Mantenimiento de aprobadores UP funciona de extremo a extremo y contabiliza correctamente. | I68: Capturas, archivo de prueba, conciliación y aprobación | J68: Todas las filiales / ajustar por ola | K68: Consultor funcional | L68: Contabilidad / Impuestos | M68: IMP-062 | N68: Finalizar IMP-062 | O68: Media | P68: 1 | Q68: 46419.75 | R68: 46422.75 | S68: =NETWORKDAYS(Q68,R68) -> 4 | V68: No iniciada | W68: 0 | X68: =IF(OR(V68="Completada",V68="No aplica"),"VERDE",IF(V68="Bloqueada","ROJO",IF(R68<TODAY(),"ROJO",IF(AND(R68-TODAY()<=7,W68<1),"AMARILLO","GRIS")))) -> GRIS
A69: IMP-064 | B69: 3. Configuración funcional | C69: Contabilidad | D69: Libros local y fiscal | E69: Configurar y validar: Libros local y fiscal | F69: 1) Levantar política para Libros local y fiscal. 2) Preparar datos. 3) Parametrizar por filial. 4) Probar escenario normal, excepción y multimoneda cuando aplique. 5) Conciliar impacto y aprobar. | G69: Libros local y fiscal: configuración, evidencia y acta | H69: Libros local y fiscal funciona de extremo a extremo y contabiliza correctamente. | I69: Capturas, archivo de prueba, conciliación y aprobación | J69: Todas las filiales / ajustar por ola | K69: Líder funcional GENTIA | L69: Contabilidad | N69: Prerrequisitos del módulo | O69: Alta | P69: 2 | Q69: 46364.75 | R69: 46367.75 | S69: =NETWORKDAYS(Q69,R69) -> 4 | V69: No iniciada | W69: 0 | X69: =IF(OR(V69="Completada",V69="No aplica"),"VERDE",IF(V69="Bloqueada","ROJO",IF(R69<TODAY(),"ROJO",IF(AND(R69-TODAY()<=7,W69<1),"AMARILLO","GRIS")))) -> GRIS
A70: IMP-065 | B70: 3. Configuración funcional | C70: Contabilidad | D70: Grupos del plan de cuentas | E70: Configurar y validar: Grupos del plan de cuentas | F70: 1) Levantar política para Grupos del plan de cuentas. 2) Preparar datos. 3) Parametrizar por filial. 4) Probar escenario normal, excepción y multimoneda cuando aplique. 5) Conciliar impacto y aprobar. | G70: Grupos del plan de cuentas: configuración, evidencia y acta | H70: Grupos del plan de cuentas funciona de extremo a extremo y contabiliza correctamente. | I70: Capturas, archivo de prueba, conciliación y aprobación | J70: Todas las filiales / ajustar por ola | K70: Líder funcional GENTIA | L70: Contabilidad | M70: IMP-064 | N70: Finalizar IMP-064 | O70: Alta | P70: 2 | Q70: 46370.75 | R70: 46372.75 | S70: =NETWORKDAYS(Q70,R70) -> 3 | V70: No iniciada | W70: 0 | X70: =IF(OR(V70="Completada",V70="No aplica"),"VERDE",IF(V70="Bloqueada","ROJO",IF(R70<TODAY(),"ROJO",IF(AND(R70-TODAY()<=7,W70<1),"AMARILLO","GRIS")))) -> GRIS
A71: IMP-066 | B71: 3. Configuración funcional | C71: Contabilidad | D71: Plan de cuentas por filial | E71: Configurar y validar: Plan de cuentas por filial | F71: 1) Levantar política para Plan de cuentas por filial. 2) Preparar datos. 3) Parametrizar por filial. 4) Probar escenario normal, excepción y multimoneda cuando aplique. 5) Conciliar impacto y aprobar. | G71: Plan de cuentas por filial: configuración, evidencia y acta | H71: Plan de cuentas por filial funciona de extremo a extremo y contabiliza correctamente. | I71: Capturas, archivo de prueba, conciliación y aprobación | J71: Todas las filiales / ajustar por ola | K71: Líder funcional GENTIA | L71: Contabilidad | M71: IMP-065 | N71: Finalizar IMP-065 | O71: Media | P71: 1 | Q71: 46373.75 | R71: 46377.75 | S71: =NETWORKDAYS(Q71,R71) -> 3 | V71: No iniciada | W71: 0 | X71: =IF(OR(V71="Completada",V71="No aplica"),"VERDE",IF(V71="Bloqueada","ROJO",IF(R71<TODAY(),"ROJO",IF(AND(R71-TODAY()<=7,W71<1),"AMARILLO","GRIS")))) -> GRIS
A72: IMP-067 | B72: 3. Configuración funcional | C72: Contabilidad | D72: Naturaleza, moneda y revaluación por cuenta | E72: Configurar y validar: Naturaleza, moneda y revaluación por cuenta | F72: 1) Levantar política para Naturaleza, moneda y revaluación por cuenta. 2) Preparar datos. 3) Parametrizar por filial. 4) Probar escenario normal, excepción y multimoneda cuando aplique. 5) Conciliar impacto y aprobar. | G72: Naturaleza, moneda y revaluación por cuenta: configuración, evidencia y acta | H72: Naturaleza, moneda y revaluación por cuenta funciona de extremo a extremo y contabiliza correctamente. | I72: Capturas, archivo de prueba, conciliación y aprobación | J72: Todas las filiales / ajustar por ola | K72: Líder funcional GENTIA | L72: Contabilidad | M72: IMP-066 | N72: Finalizar IMP-066 | O72: Alta | P72: 2 | Q72: 46378.75 | R72: 46381.75 | S72: =NETWORKDAYS(Q72,R72) -> 4 | V72: No iniciada | W72: 0 | X72: =IF(OR(V72="Completada",V72="No aplica"),"VERDE",IF(V72="Bloqueada","ROJO",IF(R72<TODAY(),"ROJO",IF(AND(R72-TODAY()<=7,W72<1),"AMARILLO","GRIS")))) -> GRIS
A73: IMP-068 | B73: 3. Configuración funcional | C73: Contabilidad | D73: Dimensiones y excepciones financieras | E73: Configurar y validar: Dimensiones y excepciones financieras | F73: 1) Levantar política para Dimensiones y excepciones financieras. 2) Preparar datos. 3) Parametrizar por filial. 4) Probar escenario normal, excepción y multimoneda cuando aplique. 5) Conciliar impacto y aprobar. | G73: Dimensiones y excepciones financieras: configuración, evidencia y acta | H73: Dimensiones y excepciones financieras funciona de extremo a extremo y contabiliza correctamente. | I73: Capturas, archivo de prueba, conciliación y aprobación | J73: Todas las filiales / ajustar por ola | K73: Líder funcional GENTIA | L73: Contabilidad | M73: IMP-067 | N73: Finalizar IMP-067 | O73: Media | P73: 1 | Q73: 46384.75 | R73: 46386.75 | S73: =NETWORKDAYS(Q73,R73) -> 3 | V73: No iniciada | W73: 0 | X73: =IF(OR(V73="Completada",V73="No aplica"),"VERDE",IF(V73="Bloqueada","ROJO",IF(R73<TODAY(),"ROJO",IF(AND(R73-TODAY()<=7,W73<1),"AMARILLO","GRIS")))) -> GRIS
A74: IMP-069 | B74: 3. Configuración funcional | C74: Contabilidad | D74: Actividad de flujo de efectivo | E74: Configurar y validar: Actividad de flujo de efectivo | F74: 1) Levantar política para Actividad de flujo de efectivo. 2) Preparar datos. 3) Parametrizar por filial. 4) Probar escenario normal, excepción y multimoneda cuando aplique. 5) Conciliar impacto y aprobar. | G74: Actividad de flujo de efectivo: configuración, evidencia y acta | H74: Actividad de flujo de efectivo funciona de extremo a extremo y contabiliza correctamente. | I74: Capturas, archivo de prueba, conciliación y aprobación | J74: Todas las filiales / ajustar por ola | K74: Líder funcional GENTIA | L74: Contabilidad | M74: IMP-068 | N74: Finalizar IMP-068 | O74: Media | P74: 1 | Q74: 46387.75 | R74: 46391.75 | S74: =NETWORKDAYS(Q74,R74) -> 3 | V74: No iniciada | W74: 0 | X74: =IF(OR(V74="Completada",V74="No aplica"),"VERDE",IF(V74="Bloqueada","ROJO",IF(R74<TODAY(),"ROJO",IF(AND(R74-TODAY()<=7,W74<1),"AMARILLO","GRIS")))) -> GRIS
A75: IMP-070 | B75: 3. Configuración funcional | C75: Contabilidad | D75: Cuentas de control CxC y CxP | E75: Configurar y validar: Cuentas de control CxC y CxP | F75: 1) Levantar política para Cuentas de control CxC y CxP. 2) Preparar datos. 3) Parametrizar por filial. 4) Probar escenario normal, excepción y multimoneda cuando aplique. 5) Conciliar impacto y aprobar. | G75: Cuentas de control CxC y CxP: configuración, evidencia y acta | H75: Cuentas de control CxC y CxP funciona de extremo a extremo y contabiliza correctamente. | I75: Capturas, archivo de prueba, conciliación y aprobación | J75: Todas las filiales / ajustar por ola | K75: Líder funcional GENTIA | L75: Contabilidad | M75: IMP-069 | N75: Finalizar IMP-069 | O75: Crítica | P75: 3 | Q75: 46392.75 | R75: 46398.75 | S75: =NETWORKDAYS(Q75,R75) -> 5 | V75: No iniciada | W75: 0 | X75: =IF(OR(V75="Completada",V75="No aplica"),"VERDE",IF(V75="Bloqueada","ROJO",IF(R75<TODAY(),"ROJO",IF(AND(R75-TODAY()<=7,W75<1),"AMARILLO","GRIS")))) -> GRIS
A76: IMP-071 | B76: 3. Configuración funcional | C76: Contabilidad | D76: Cuentas intercompany Expense y Caja Chica | E76: Configurar y validar: Cuentas intercompany Expense y Caja Chica | F76: 1) Levantar política para Cuentas intercompany Expense y Caja Chica. 2) Preparar datos. 3) Parametrizar por filial. 4) Probar escenario normal, excepción y multimoneda cuando aplique. 5) Conciliar impacto y aprobar. | G76: Cuentas intercompany Expense y Caja Chica: configuración, evidencia y acta | H76: Cuentas intercompany Expense y Caja Chica funciona de extremo a extremo y contabiliza correctamente. | I76: Capturas, archivo de prueba, conciliación y aprobación | J76: Todas las filiales / ajustar por ola | K76: Líder funcional GENTIA | L76: Contabilidad | M76: IMP-070 | N76: Finalizar IMP-070 | O76: Alta | P76: 2 | Q76: 46399.75 | R76: 46401.75 | S76: =NETWORKDAYS(Q76,R76) -> 3 | V76: No iniciada | W76: 0 | X76: =IF(OR(V76="Completada",V76="No aplica"),"VERDE",IF(V76="Bloqueada","ROJO",IF(R76<TODAY(),"ROJO",IF(AND(R76-TODAY()<=7,W76<1),"AMARILLO","GRIS")))) -> GRIS
A77: IMP-072 | B77: 3. Configuración funcional | C77: Contabilidad | D77: Cuentas bancarias anticipos e impuestos | E77: Configurar y validar: Cuentas bancarias anticipos e impuestos | F77: 1) Levantar política para Cuentas bancarias anticipos e impuestos. 2) Preparar datos. 3) Parametrizar por filial. 4) Probar escenario normal, excepción y multimoneda cuando aplique. 5) Conciliar impacto y aprobar. | G77: Cuentas bancarias anticipos e impuestos: configuración, evidencia y acta | H77: Cuentas bancarias anticipos e impuestos funciona de extremo a extremo y contabiliza correctamente. | I77: Capturas, archivo de prueba, conciliación y aprobación | J77: Todas las filiales / ajustar por ola | K77: Líder funcional GENTIA | L77: Contabilidad | M77: IMP-071 | N77: Finalizar IMP-071 | O77: Alta | P77: 2 | Q77: 46402.75 | R77: 46406.75 | S77: =NETWORKDAYS(Q77,R77) -> 3 | V77: No iniciada | W77: 0 | X77: =IF(OR(V77="Completada",V77="No aplica"),"VERDE",IF(V77="Bloqueada","ROJO",IF(R77<TODAY(),"ROJO",IF(AND(R77-TODAY()<=7,W77<1),"AMARILLO","GRIS")))) -> GRIS
A78: IMP-073 | B78: 3. Configuración funcional | C78: Contabilidad | D78: Reglas de asignación contable | E78: Configurar y validar: Reglas de asignación contable | F78: 1) Levantar política para Reglas de asignación contable. 2) Preparar datos. 3) Parametrizar por filial. 4) Probar escenario normal, excepción y multimoneda cuando aplique. 5) Conciliar impacto y aprobar. | G78: Reglas de asignación contable: configuración, evidencia y acta | H78: Reglas de asignación contable funciona de extremo a extremo y contabiliza correctamente. | I78: Capturas, archivo de prueba, conciliación y aprobación | J78: Todas las filiales / ajustar por ola | K78: Líder funcional GENTIA | L78: Contabilidad | M78: IMP-072 | N78: Finalizar IMP-072 | O78: Media | P78: 1 | Q78: 46407.75 | R78: 46412.75 | S78: =NETWORKDAYS(Q78,R78) -> 4 | V78: No iniciada | W78: 0 | X78: =IF(OR(V78="Completada",V78="No aplica"),"VERDE",IF(V78="Bloqueada","ROJO",IF(R78<TODAY(),"ROJO",IF(AND(R78-TODAY()<=7,W78<1),"AMARILLO","GRIS")))) -> GRIS
A79: IMP-074 | B79: 3. Configuración funcional | C79: Contabilidad | D79: Asientos manuales y recurrentes | E79: Configurar y validar: Asientos manuales y recurrentes | F79: 1) Levantar política para Asientos manuales y recurrentes. 2) Preparar datos. 3) Parametrizar por filial. 4) Probar escenario normal, excepción y multimoneda cuando aplique. 5) Conciliar impacto y aprobar. | G79: Asientos manuales y recurrentes: configuración, evidencia y acta | H79: Asientos manuales y recurrentes funciona de extremo a extremo y contabiliza correctamente. | I79: Capturas, archivo de prueba, conciliación y aprobación | J79: Todas las filiales / ajustar por ola | K79: Líder funcional GENTIA | L79: Contabilidad | M79: IMP-073 | N79: Finalizar IMP-073 | O79: Media | P79: 1 | Q79: 46413.75 | R79: 46415.75 | S79: =NETWORKDAYS(Q79,R79) -> 3 | V79: No iniciada | W79: 0 | X79: =IF(OR(V79="Completada",V79="No aplica"),"VERDE",IF(V79="Bloqueada","ROJO",IF(R79<TODAY(),"ROJO",IF(AND(R79-TODAY()<=7,W79<1),"AMARILLO","GRIS")))) -> GRIS
A80: IMP-075 | B80: 3. Configuración funcional | C80: Contabilidad | D80: Importación masiva de asientos | E80: Configurar y validar: Importación masiva de asientos | F80: 1) Levantar política para Importación masiva de asientos. 2) Preparar datos. 3) Parametrizar por filial. 4) Probar escenario normal, excepción y multimoneda cuando aplique. 5) Conciliar impacto y aprobar. | G80: Importación masiva de asientos: configuración, evidencia y acta | H80: Importación masiva de asientos funciona de extremo a extremo y contabiliza correctamente. | I80: Capturas, archivo de prueba, conciliación y aprobación | J80: Todas las filiales / ajustar por ola | K80: Líder funcional GENTIA | L80: Contabilidad | M80: IMP-074 | N80: Finalizar IMP-074 | O80: Media | P80: 1 | Q80: 46416.75 | R80: 46420.75 | S80: =NETWORKDAYS(Q80,R80) -> 3 | V80: No iniciada | W80: 0 | X80: =IF(OR(V80="Completada",V80="No aplica"),"VERDE",IF(V80="Bloqueada","ROJO",IF(R80<TODAY(),"ROJO",IF(AND(R80-TODAY()<=7,W80<1),"AMARILLO","GRIS")))) -> GRIS
A81: IMP-076 | B81: 3. Configuración funcional | C81: Contabilidad | D81: ASI_NOM ASI_LIQ ASI_DIA y mes de servicio | E81: Configurar y validar: ASI_NOM ASI_LIQ ASI_DIA y mes de servicio | F81: 1) Levantar política para ASI_NOM ASI_LIQ ASI_DIA y mes de servicio. 2) Preparar datos. 3) Parametrizar por filial. 4) Probar escenario normal, excepción y multimoneda cuando aplique. 5) Conciliar impacto y aprobar. | G81: ASI_NOM ASI_LIQ ASI_DIA y mes de servicio: configuración, evidencia y acta | H81: ASI_NOM ASI_LIQ ASI_DIA y mes de servicio funciona de extremo a extremo y contabiliza correctamente. | I81: Capturas, archivo de prueba, conciliación y aprobación | J81: Todas las filiales / ajustar por ola | K81: Líder funcional GENTIA | L81: Contabilidad | M81: IMP-075 | N81: Finalizar IMP-075 | O81: Media | P81: 1 | Q81: 46421.75 | R81: 46426.75 | S81: =NETWORKDAYS(Q81,R81) -> 4 | V81: No iniciada | W81: 0 | X81: =IF(OR(V81="Completada",V81="No aplica"),"VERDE",IF(V81="Bloqueada","ROJO",IF(R81<TODAY(),"ROJO",IF(AND(R81-TODAY()<=7,W81<1),"AMARILLO","GRIS")))) -> GRIS
... A84: IMP-079 | B84: 3. Configuración funcional | C84: Contabilidad | D84: Revaluación de moneda extranjera | E84: Configurar y validar: Revaluación de moneda extranjera | F84: 1) Levantar política para Revaluación de moneda extranjera. 2) Preparar datos. 3) Parametrizar por filial. 4) Probar escenario normal, excepción y multimoneda cuando aplique. 5) Conciliar impacto y aprobar. | G84: Revaluación de moneda extranjera: configuración, evidencia y acta | H84: Revaluación de moneda extranjera funciona de extremo a extremo y contabiliza correctamente. | I84: Capturas, archivo de prueba, conciliación y aprobación | J84: Todas las filiales / ajustar por ola | K84: Líder funcional GENTIA | L84: Contabilidad | M84: IMP-078 | N84: Finalizar IMP-078 | O84: Alta | P84: 2 | Q84: 46435.75 | R84: 46440.75 | S84: =NETWORKDAYS(Q84,R84) -> 4 | V84: No iniciada | W84: 0 | X84: =IF(OR(V84="Completada",V84="No aplica"),"VERDE",IF(V84="Bloqueada","ROJO",IF(R84<TODAY(),"ROJO",IF(AND(R84-TODAY()<=7,W84<1),"AMARILLO","GRIS")))) -> GRIS
A85: IMP-080 | B85: 3. Configuración funcional | C85: Motor de transacciones | D85: Tipos de transacción | E85: Configurar y validar: Tipos de transacción | F85: 1) Diseñar Tipos de transacción. 2) Configurar primero en pruebas sin exponer secretos. 3) Ejecutar prueba positiva, negativa y recuperación. 4) Documentar monitoreo y rollback. 5) Promover con aprobación. | G85: Tipos de transacción: configuración, evidencia y acta | H85: Tipos de transacción opera en pruebas y producción, sin secretos expuestos, con monitoreo y rollback verificado. | I85: Capturas, archivo de prueba, conciliación y aprobación | J85: Todas las filiales / ajustar por ola | K85: Líder técnico | L85: Contabilidad | N85: Prerrequisitos del módulo | O85: Alta | P85: 2 | Q85: 46365.75 | R85: 46370.75 | S85: =NETWORKDAYS(Q85,R85) -> 4 | V85: No iniciada | W85: 0 | X85: =IF(OR(V85="Completada",V85="No aplica"),"VERDE",IF(V85="Bloqueada","ROJO",IF(R85<TODAY(),"ROJO",IF(AND(R85-TODAY()<=7,W85<1),"AMARILLO","GRIS")))) -> GRIS
A86: IMP-081 | B86: 3. Configuración funcional | C86: Motor de transacciones | D86: Encabezados y líneas | E86: Configurar y validar: Encabezados y líneas | F86: 1) Diseñar Encabezados y líneas. 2) Configurar primero en pruebas sin exponer secretos. 3) Ejecutar prueba positiva, negativa y recuperación. 4) Documentar monitoreo y rollback. 5) Promover con aprobación. | G86: Encabezados y líneas: configuración, evidencia y acta | H86: Encabezados y líneas opera en pruebas y producción, sin secretos expuestos, con monitoreo y rollback verificado. | I86: Capturas, archivo de prueba, conciliación y aprobación | J86: Todas las filiales / ajustar por ola | K86: Líder técnico | L86: Contabilidad | M86: IMP-080 | N86: Finalizar IMP-080 | O86: Alta | P86: 2 | Q86: 46371.75 | R86: 46373.75 | S86: =NETWORKDAYS(Q86,R86) -> 3 | V86: No iniciada | W86: 0 | X86: =IF(OR(V86="Completada",V86="No aplica"),"VERDE",IF(V86="Bloqueada","ROJO",IF(R86<TODAY(),"ROJO",IF(AND(R86-TODAY()<=7,W86<1),"AMARILLO","GRIS")))) -> GRIS
A87: IMP-082 | B87: 3. Configuración funcional | C87: Motor de transacciones | D87: Dimensiones transaccionales | E87: Configurar y validar: Dimensiones transaccionales | F87: 1) Diseñar Dimensiones transaccionales. 2) Configurar primero en pruebas sin exponer secretos. 3) Ejecutar prueba positiva, negativa y recuperación. 4) Documentar monitoreo y rollback. 5) Promover con aprobación. | G87: Dimensiones transaccionales: configuración, evidencia y acta | H87: Dimensiones transaccionales opera en pruebas y producción, sin secretos expuestos, con monitoreo y rollback verificado. | I87: Capturas, archivo de prueba, conciliación y aprobación | J87: Todas las filiales / ajustar por ola | K87: Líder técnico | L87: Contabilidad | M87: IMP-081 | N87: Finalizar IMP-081 | O87: Media | P87: 1 | Q87: 46374.75 | R87: 46378.75 | S87: =NETWORKDAYS(Q87,R87) -> 3 | V87: No iniciada | W87: 0 | X87: =IF(OR(V87="Completada",V87="No aplica"),"VERDE",IF(V87="Bloqueada","ROJO",IF(R87<TODAY(),"ROJO",IF(AND(R87-TODAY()<=7,W87<1),"AMARILLO","GRIS")))) -> GRIS
A88: IMP-083 | B88: 3. Configuración funcional | C88: Motor de transacciones | D88: Impactos contables | E88: Configurar y validar: Impactos contables | F88: 1) Diseñar Impactos contables. 2) Configurar primero en pruebas sin exponer secretos. 3) Ejecutar prueba positiva, negativa y recuperación. 4) Documentar monitoreo y rollback. 5) Promover con aprobación. | G88: Impactos contables: configuración, evidencia y acta | H88: Impactos contables opera en pruebas y producción, sin secretos expuestos, con monitoreo y rollback verificado. | I88: Capturas, archivo de prueba, conciliación y aprobación | J88: Todas las filiales / ajustar por ola | K88: Líder técnico | L88: Contabilidad | M88: IMP-082 | N88: Finalizar IMP-082 | O88: Media | P88: 1 | Q88: 46379.75 | R88: 46384.75 | S88: =NETWORKDAYS(Q88,R88) -> 4 | V88: No iniciada | W88: 0 | X88: =IF(OR(V88="Completada",V88="No aplica"),"VERDE",IF(V88="Bloqueada","ROJO",IF(R88<TODAY(),"ROJO",IF(AND(R88-TODAY()<=7,W88<1),"AMARILLO","GRIS")))) -> GRIS
A89: IMP-084 | B89: 3. Configuración funcional | C89: Motor de transacciones | D89: Reglas de débito y crédito | E89: Configurar y validar: Reglas de débito y crédito | F89: 1) Diseñar Reglas de débito y crédito. 2) Configurar primero en pruebas sin exponer secretos. 3) Ejecutar prueba positiva, negativa y recuperación. 4) Documentar monitoreo y rollback. 5) Promover con aprobación. | G89: Reglas de débito y crédito: configuración, evidencia y acta | H89: Reglas de débito y crédito opera en pruebas y producción, sin secretos expuestos, con monitoreo y rollback verificado. | I89: Capturas, archivo de prueba, conciliación y aprobación | J89: Todas las filiales / ajustar por ola | K89: Líder técnico | L89: Contabilidad | M89: IMP-083 | N89: Finalizar IMP-083 | O89: Media | P89: 1 | Q89: 46385.75 | R89: 46387.75 | S89: =NETWORKDAYS(Q89,R89) -> 3 | V89: No iniciada | W89: 0 | X89: =IF(OR(V89="Completada",V89="No aplica"),"VERDE",IF(V89="Bloqueada","ROJO",IF(R89<TODAY(),"ROJO",IF(AND(R89-TODAY()<=7,W89<1),"AMARILLO","GRIS")))) -> GRIS
A90: IMP-085 | B90: 3. Configuración funcional | C90: Motor de transacciones | D90: Idempotencia | E90: Configurar y validar: Idempotencia | F90: 1) Diseñar Idempotencia. 2) Configurar primero en pruebas sin exponer secretos. 3) Ejecutar prueba positiva, negativa y recuperación. 4) Documentar monitoreo y rollback. 5) Promover con aprobación. | G90: Idempotencia: configuración, evidencia y acta | H90: Idempotencia opera en pruebas y producción, sin secretos expuestos, con monitoreo y rollback verificado. | I90: Capturas, archivo de prueba, conciliación y aprobación | J90: Todas las filiales / ajustar por ola | K90: Líder técnico | L90: Contabilidad | M90: IMP-084 | N90: Finalizar IMP-084 | O90: Media | P90: 1 | Q90: 46388.75 | R90: 46392.75 | S90: =NETWORKDAYS(Q90,R90) -> 3 | V90: No iniciada | W90: 0 | X90: =IF(OR(V90="Completada",V90="No aplica"),"VERDE",IF(V90="Bloqueada","ROJO",IF(R90<TODAY(),"ROJO",IF(AND(R90-TODAY()<=7,W90<1),"AMARILLO","GRIS")))) -> GRIS
A91: IMP-086 | B91: 3. Configuración funcional | C91: Motor de transacciones | D91: Trazabilidad documento-asiento | E91: Configurar y validar: Trazabilidad documento-asiento | F91: 1) Diseñar Trazabilidad documento-asiento. 2) Configurar primero en pruebas sin exponer secretos. 3) Ejecutar prueba positiva, negativa y recuperación. 4) Documentar monitoreo y rollback. 5) Promover con aprobación. | G91: Trazabilidad documento-asiento: configuración, evidencia y acta | H91: Trazabilidad documento-asiento opera en pruebas y producción, sin secretos expuestos, con monitoreo y rollback verificado. | I91: Capturas, archivo de prueba, conciliación y aprobación | J91: Todas las filiales / ajustar por ola | K91: Líder técnico | L91: Contabilidad | M91: IMP-085 | N91: Finalizar IMP-085 | O91: Media | P91: 1 | Q91: 46393.75 | R91: 46398.75 | S91: =NETWORKDAYS(Q91,R91) -> 4 | V91: No iniciada | W91: 0 | X91: =IF(OR(V91="Completada",V91="No aplica"),"VERDE",IF(V91="Bloqueada","ROJO",IF(R91<TODAY(),"ROJO",IF(AND(R91-TODAY()<=7,W91<1),"AMARILLO","GRIS")))) -> GRIS
A92: IMP-087 | B92: 3. Configuración funcional | C92: Motor de transacciones | D92: Partida doble al centavo | E92: Configurar y validar: Partida doble al centavo | F92: 1) Diseñar Partida doble al centavo. 2) Configurar primero en pruebas sin exponer secretos. 3) Ejecutar prueba positiva, negativa y recuperación. 4) Documentar monitoreo y rollback. 5) Promover con aprobación. | G92: Partida doble al centavo: configuración, evidencia y acta | H92: Partida doble al centavo opera en pruebas y producción, sin secretos expuestos, con monitoreo y rollback verificado. | I92: Capturas, archivo de prueba, conciliación y aprobación | J92: Todas las filiales / ajustar por ola | K92: Líder técnico | L92: Contabilidad | M92: IMP-086 | N92: Finalizar IMP-086 | O92: Crítica | P92: 3 | Q92: 46399.75 | R92: 46405.75 | S92: =NETWORKDAYS(Q92,R92) -> 5 | V92: No iniciada | W92: 0 | X92: =IF(OR(V92="Completada",V92="No aplica"),"VERDE",IF(V92="Bloqueada","ROJO",IF(R92<TODAY(),"ROJO",IF(AND(R92-TODAY()<=7,W92<1),"AMARILLO","GRIS")))) -> GRIS
A93: IMP-088 | B93: 3. Configuración funcional | C93: Entidades | D93: Clientes e identificaciones fiscales | E93: Migrar y conciliar: Clientes e identificaciones fiscales | F93: 1) Identificar fuente y propietario de Clientes e identificaciones fiscales. 2) Extraer y perfilar. 3) Limpiar, homologar y mapear. 4) Cargar en pruebas. 5) Conciliar registros, importes y rechazados. 6) Firmar aprobación. | G93: Clientes e identificaciones fiscales: configuración, evidencia y acta | H93: Clientes e identificaciones fiscales: registros válidos cargados, rechazados justificados y diferencia monetaria 0,00; conciliación firmada. | I93: Capturas, archivo de prueba, conciliación y aprobación | J93: Todas las filiales / ajustar por ola | K93: Consultor de datos | L93: Dueño de datos | N93: Prerrequisitos del módulo | O93: Alta | P93: 2 | Q93: 46366.75 | R93: 46371.75 | S93: =NETWORKDAYS(Q93,R93) -> 4 | V93: No iniciada | W93: 0 | X93: =IF(OR(V93="Completada",V93="No aplica"),"VERDE",IF(V93="Bloqueada","ROJO",IF(R93<TODAY(),"ROJO",IF(AND(R93-TODAY()<=7,W93<1),"AMARILLO","GRIS")))) -> GRIS
A94: IMP-089 | B94: 3. Configuración funcional | C94: Entidades | D94: Proveedores y categorías | E94: Migrar y conciliar: Proveedores y categorías | F94: 1) Identificar fuente y propietario de Proveedores y categorías. 2) Extraer y perfilar. 3) Limpiar, homologar y mapear. 4) Cargar en pruebas. 5) Conciliar registros, importes y rechazados. 6) Firmar aprobación. | G94: Proveedores y categorías: configuración, evidencia y acta | H94: Proveedores y categorías: registros válidos cargados, rechazados justificados y diferencia monetaria 0,00; conciliación firmada. | I94: Capturas, archivo de prueba, conciliación y aprobación | J94: Todas las filiales / ajustar por ola | K94: Consultor de datos | L94: Dueño de datos | M94: IMP-088 | N94: Finalizar IMP-088 | O94: Alta | P94: 2 | Q94: 46372.75 | R94: 46374.75 | S94: =NETWORKDAYS(Q94,R94) -> 3 | V94: No iniciada | W94: 0 | X94: =IF(OR(V94="Completada",V94="No aplica"),"VERDE",IF(V94="Bloqueada","ROJO",IF(R94<TODAY(),"ROJO",IF(AND(R94-TODAY()<=7,W94<1),"AMARILLO","GRIS")))) -> GRIS
A95: IMP-090 | B95: 3. Configuración funcional | C95: Entidades | D95: Empleados | E95: Migrar y conciliar: Empleados | F95: 1) Identificar fuente y propietario de Empleados. 2) Extraer y perfilar. 3) Limpiar, homologar y mapear. 4) Cargar en pruebas. 5) Conciliar registros, importes y rechazados. 6) Firmar aprobación. | G95: Empleados: configuración, evidencia y acta | H95: Empleados: registros válidos cargados, rechazados justificados y diferencia monetaria 0,00; conciliación firmada. | I95: Capturas, archivo de prueba, conciliación y aprobación | J95: Todas las filiales / ajustar por ola | K95: Consultor de datos | L95: Dueño de datos | M95: IMP-089 | N95: Finalizar IMP-089 | O95: Media | P95: 1 | Q95: 46377.75 | R95: 46379.75 | S95: =NETWORKDAYS(Q95,R95) -> 3 | V95: No iniciada | W95: 0 | X95: =IF(OR(V95="Completada",V95="No aplica"),"VERDE",IF(V95="Bloqueada","ROJO",IF(R95<TODAY(),"ROJO",IF(AND(R95-TODAY()<=7,W95<1),"AMARILLO","GRIS")))) -> GRIS
A96: IMP-091 | B96: 3. Configuración funcional | C96: Entidades | D96: Entidades por subsidiaria | E96: Migrar y conciliar: Entidades por subsidiaria | F96: 1) Identificar fuente y propietario de Entidades por subsidiaria. 2) Extraer y perfilar. 3) Limpiar, homologar y mapear. 4) Cargar en pruebas. 5) Conciliar registros, importes y rechazados. 6) Firmar aprobación. | G96: Entidades por subsidiaria: configuración, evidencia y acta | H96: Entidades por subsidiaria: registros válidos cargados, rechazados justificados y diferencia monetaria 0,00; conciliación firmada. | I96: Capturas, archivo de prueba, conciliación y aprobación | J96: Todas las filiales / ajustar por ola | K96: Consultor de datos | L96: Dueño de datos | M96: IMP-090 | N96: Finalizar IMP-090 | O96: Media | P96: 1 | Q96: 46380.75 | R96: 46385.75 | S96: =NETWORKDAYS(Q96,R96) -> 4 | V96: No iniciada | W96: 0 | X96: =IF(OR(V96="Completada",V96="No aplica"),"VERDE",IF(V96="Bloqueada","ROJO",IF(R96<TODAY(),"ROJO",IF(AND(R96-TODAY()<=7,W96<1),"AMARILLO","GRIS")))) -> GRIS
A97: IMP-092 | B97: 3. Configuración funcional | C97: Entidades | D97: Monedas autorizadas | E97: Migrar y conciliar: Monedas autorizadas | F97: 1) Identificar fuente y propietario de Monedas autorizadas. 2) Extraer y perfilar. 3) Limpiar, homologar y mapear. 4) Cargar en pruebas. 5) Conciliar registros, importes y rechazados. 6) Firmar aprobación. | G97: Monedas autorizadas: configuración, evidencia y acta | H97: Monedas autorizadas: registros válidos cargados, rechazados justificados y diferencia monetaria 0,00; conciliación firmada. | I97: Capturas, archivo de prueba, conciliación y aprobación | J97: Todas las filiales / ajustar por ola | K97: Consultor de datos | L97: Dueño de datos | M97: IMP-091 | N97: Finalizar IMP-091 | O97: Media | P97: 1 | Q97: 46386.75 | R97: 46388.75 | S97: =NETWORKDAYS(Q97,R97) -> 3 | V97: No iniciada | W97: 0 | X97: =IF(OR(V97="Completada",V97="No aplica"),"VERDE",IF(V97="Bloqueada","ROJO",IF(R97<TODAY(),"ROJO",IF(AND(R97-TODAY()<=7,W97<1),"AMARILLO","GRIS")))) -> GRIS
A98: IMP-093 | B98: 3. Configuración funcional | C98: Entidades | D98: Términos y límites de crédito | E98: Migrar y conciliar: Términos y límites de crédito | F98: 1) Identificar fuente y propietario de Términos y límites de crédito. 2) Extraer y perfilar. 3) Limpiar, homologar y mapear. 4) Cargar en pruebas. 5) Conciliar registros, importes y rechazados. 6) Firmar aprobación. | G98: Términos y límites de crédito: configuración, evidencia y acta | H98: Términos y límites de crédito: registros válidos cargados, rechazados justificados y diferencia monetaria 0,00; conciliación firmada. | I98: Capturas, archivo de prueba, conciliación y aprobación | J98: Todas las filiales / ajustar por ola | K98: Consultor de datos | L98: Dueño de datos | M98: IMP-092 | N98: Finalizar IMP-092 | O98: Media | P98: 1 | Q98: 46391.75 | R98: 46393.75 | S98: =NETWORKDAYS(Q98,R98) -> 3 | V98: No iniciada | W98: 0 | X98: =IF(OR(V98="Completada",V98="No aplica"),"VERDE",IF(V98="Bloqueada","ROJO",IF(R98<TODAY(),"ROJO",IF(AND(R98-TODAY()<=7,W98<1),"AMARILLO","GRIS")))) -> GRIS
A99: IMP-094 | B99: 3. Configuración funcional | C99: Entidades | D99: Retenciones por tercero | E99: Migrar y conciliar: Retenciones por tercero | F99: 1) Identificar fuente y propietario de Retenciones por tercero. 2) Extraer y perfilar. 3) Limpiar, homologar y mapear. 4) Cargar en pruebas. 5) Conciliar registros, importes y rechazados. 6) Firmar aprobación. | G99: Retenciones por tercero: configuración, evidencia y acta | H99: Retenciones por tercero: registros válidos cargados, rechazados justificados y diferencia monetaria 0,00; conciliación firmada. | I99: Capturas, archivo de prueba, conciliación y aprobación | J99: Todas las filiales / ajustar por ola | K99: Consultor de datos | L99: Dueño de datos | M99: IMP-093 | N99: Finalizar IMP-093 | O99: Media | P99: 1 | Q99: 46394.75 | R99: 46399.75 | S99: =NETWORKDAYS(Q99,R99) -> 4 | V99: No iniciada | W99: 0 | X99: =IF(OR(V99="Completada",V99="No aplica"),"VERDE",IF(V99="Bloqueada","ROJO",IF(R99<TODAY(),"ROJO",IF(AND(R99-TODAY()<=7,W99<1),"AMARILLO","GRIS")))) -> GRIS
A100: IMP-095 | B100: 3. Configuración funcional | C100: Entidades | D100: Clientes y proveedores intercompany | E100: Migrar y conciliar: Clientes y proveedores intercompany | F100: 1) Identificar fuente y propietario de Clientes y proveedores intercompany. 2) Extraer y perfilar. 3) Limpiar, homologar y mapear. 4) Cargar en pruebas. 5) Conciliar registros, importes y rechazados. 6) Firmar aprobación. | G100: Clientes y proveedores intercompany: configuración, evidencia y acta | H100: Clientes y proveedores intercompany: registros válidos cargados, rechazados justificados y diferencia monetaria 0,00; conciliación firmada. | I100: Capturas, archivo de prueba, conciliación y aprobación | J100: Todas las filiales / ajustar por ola | K100: Consultor de datos | L100: Dueño de datos | M100: IMP-094 | N100: Finalizar IMP-094 | O100: Alta | P100: 2 | Q100: 46400.75 | R100: 46402.75 | S100: =NETWORKDAYS(Q100,R100) -> 3 | V100: No iniciada | W100: 0 | X100: =IF(OR(V100="Completada",V100="No aplica"),"VERDE",IF(V100="Bloqueada","ROJO",IF(R100<TODAY(),"ROJO",IF(AND(R100-TODAY()<=7,W100<1),"AMARILLO","GRIS")))) -> GRIS
A101: IMP-096 | B101: 3. Configuración funcional | C101: Entidades | D101: Agencias tributarias | E101: Migrar y conciliar: Agencias tributarias | F101: 1) Identificar fuente y propietario de Agencias tributarias. 2) Extraer y perfilar. 3) Limpiar, homologar y mapear. 4) Cargar en pruebas. 5) Conciliar registros, importes y rechazados. 6) Firmar aprobación. | G101: Agencias tributarias: configuración, evidencia y acta | H101: Agencias tributarias: registros válidos cargados, rechazados justificados y diferencia monetaria 0,00; conciliación firmada. | I101: Capturas, archivo de prueba, conciliación y aprobación | J101: Todas las filiales / ajustar por ola | K101: Consultor de datos | L101: Dueño de datos | M101: IMP-095 | N101: Finalizar IMP-095 | O101: Media | P101: 1 | Q101: 46405.75 | R101: 46407.75 | S101: =NETWORKDAYS(Q101,R101) -> 3 | V101: No iniciada | W101: 0 | X101: =IF(OR(V101="Completada",V101="No aplica"),"VERDE",IF(V101="Bloqueada","ROJO",IF(R101<TODAY(),"ROJO",IF(AND(R101-TODAY()<=7,W101<1),"AMARILLO","GRIS")))) -> GRIS
A102: IMP-097 | B102: 3. Configuración funcional | C102: Entidades | D102: Datos bancarios del tercero | E102: Migrar y conciliar: Datos bancarios del tercero | F102: 1) Identificar fuente y propietario de Datos bancarios del tercero. 2) Extraer y perfilar. 3) Limpiar, homologar y mapear. 4) Cargar en pruebas. 5) Conciliar registros, importes y rechazados. 6) Firmar aprobación. | G102: Datos bancarios del tercero: configuración, evidencia y acta | H102: Datos bancarios del tercero: registros válidos cargados, rechazados justificados y diferencia monetaria 0,00; conciliación firmada. | I102: Capturas, archivo de prueba, conciliación y aprobación | J102: Todas las filiales / ajustar por ola | K102: Consultor de datos | L102: Dueño de datos | M102: IMP-096 | N102: Finalizar IMP-096 | O102: Media | P102: 1 | Q102: 46408.75 | R102: 46413.75 | S102: =NETWORKDAYS(Q102,R102) -> 4 | V102: No iniciada | W102: 0 | X102: =IF(OR(V102="Completada",V102="No aplica"),"VERDE",IF(V102="Bloqueada","ROJO",IF(R102<TODAY(),"ROJO",IF(AND(R102-TODAY()<=7,W102<1),"AMARILLO","GRIS")))) -> GRIS
A103: IMP-098 | B103: 4. Procesos operativos | C103: Ventas y Cuentas por Cobrar | D103: Listas de precios | E103: Configurar y validar: Listas de precios | F103: 1) Levantar política para Listas de precios. 2) Preparar datos. 3) Parametrizar por filial. 4) Probar escenario normal, excepción y multimoneda cuando aplique. 5) Conciliar impacto y aprobar. | G103: Listas de precios: configuración, evidencia y acta | H103: Listas de precios funciona de extremo a extremo y contabiliza correctamente. | I103: Capturas, archivo de prueba, conciliación y aprobación | J103: Todas las filiales / ajustar por ola | K103: Consultor funcional | L103: Ventas / CxC | N103: Prerrequisitos del módulo | O103: Alta | P103: 2 | Q103: 46395.75 | R103: 46400.75 | S103: =NETWORKDAYS(Q103,R103) -> 4 | V103: No iniciada | W103: 0 | X103: =IF(OR(V103="Completada",V103="No aplica"),"VERDE",IF(V103="Bloqueada","ROJO",IF(R103<TODAY(),"ROJO",IF(AND(R103-TODAY()<=7,W103<1),"AMARILLO","GRIS")))) -> GRIS
A104: IMP-099 | B104: 4. Procesos operativos | C104: Ventas y Cuentas por Cobrar | D104: Cotizaciones | E104: Configurar y validar: Cotizaciones | F104: 1) Levantar política para Cotizaciones. 2) Preparar datos. 3) Parametrizar por filial. 4) Probar escenario normal, excepción y multimoneda cuando aplique. 5) Conciliar impacto y aprobar. | G104: Cotizaciones: configuración, evidencia y acta | H104: Cotizaciones funciona de extremo a extremo y contabiliza correctamente. | I104: Capturas, archivo de prueba, conciliación y aprobación | J104: Todas las filiales / ajustar por ola | K104: Consultor funcional | L104: Ventas / CxC | M104: IMP-098 | N104: Finalizar IMP-098 | O104: Alta | P104: 2 | Q104: 46401.75 | R104: 46405.75 | S104: =NETWORKDAYS(Q104,R104) -> 3 | V104: No iniciada | W104: 0 | X104: =IF(OR(V104="Completada",V104="No aplica"),"VERDE",IF(V104="Bloqueada","ROJO",IF(R104<TODAY(),"ROJO",IF(AND(R104-TODAY()<=7,W104<1),"AMARILLO","GRIS")))) -> GRIS
...

Sheet 03_Rollout_Filiales
A1: ROLLOUT POR FILIAL
A2: Matriz preservada del archivo de referencia, mejorada con fases y avance dinámico.
A5: ID | B5: Subsidiaria | C5: País | D5: Gobierno | E5: Maestros | F5: Seguridad | G5: Configuración | H5: Migración | I5: UAT | J5: Capacitación | K5: Cutover | L5: Estado general | M5: % preparación | N5: Go-Live | O5: Responsable | P5: Observaciones
A6: FIL-01 | B6: S.T.T. HOLDINGS LIMITED - Jamaica | D6: No iniciada | E6: No iniciada | F6: No iniciada | G6: No iniciada | H6: No iniciada | I6: No iniciada | J6: No iniciada | K6: No iniciada | L6: No iniciada | M6: =COUNTIF(D6:K6,"Completada")/8 -> 0 | N6: 46496.75
A7: FIL-02 | B7: TOTAL TALENT ECUADOR TOTAECUA S.A. - Ecuador | D7: No iniciada | E7: No iniciada | F7: No iniciada | G7: No iniciada | H7: No iniciada | I7: No iniciada | J7: No iniciada | K7: No iniciada | L7: No iniciada | M7: =COUNTIF(D7:K7,"Completada")/8 -> 0 | N7: 46496.75
A8: FIL-03 | B8: EBO, S.A. DE C.V (EL SALVADOR) | D8: No iniciada | E8: No iniciada | F8: No iniciada | G8: No iniciada | H8: No iniciada | I8: No iniciada | J8: No iniciada | K8: No iniciada | L8: No iniciada | M8: =COUNTIF(D8:K8,"Completada")/8 -> 0 | N8: 46496.75
A9: FIL-04 | B9: STT TECHNOLOGY & SOLUTIONS, INC - Panamá | D9: No iniciada | E9: No iniciada | F9: No iniciada | G9: No iniciada | H9: No iniciada | I9: No iniciada | J9: No iniciada | K9: No iniciada | L9: No iniciada | M9: =COUNTIF(D9:K9,"Completada")/8 -> 0 | N9: 46496.75
A10: FIL-05 | B10: HR SOLUTIONS PERU S.A.C. | D10: No iniciada | E10: No iniciada | F10: No iniciada | G10: No iniciada | H10: No iniciada | I10: No iniciada | J10: No iniciada | K10: No iniciada | L10: No iniciada | M10: =COUNTIF(D10:K10,"Completada")/8 -> 0 | N10: 46496.75
A11: FIL-06 | B11: PAYROLL OUTSOURCING S.A. - Costa Rica | D11: No iniciada | E11: No iniciada | F11: No iniciada | G11: No iniciada | H11: No iniciada | I11: No iniciada | J11: No iniciada | K11: No iniciada | L11: No iniciada | M11: =COUNTIF(D11:K11,"Completada")/8 -> 0 | N11: 46496.75
A12: FIL-07 | B12: INFORMATION TECHNOLOGY OUTSOURCING IN C.L.O.U.D S.A. - Costa Rica | D12: No iniciada | E12: No iniciada | F12: No iniciada | G12: No iniciada | H12: No iniciada | I12: No iniciada | J12: No iniciada | K12: No iniciada | L12: No iniciada | M12: =COUNTIF(D12:K12,"Completada")/8 -> 0 | N12: 46496.75
A13: FIL-08 | B13: STT GROUP DE CR S.A. - Costa Rica | D13: No iniciada | E13: No iniciada | F13: No iniciada | G13: No iniciada | H13: No iniciada | I13: No iniciada | J13: No iniciada | K13: No iniciada | L13: No iniciada | M13: =COUNTIF(D13:K13,"Completada")/8 -> 0 | N13: 46496.75
A14: FIL-09 | B14: STT CAPITAL DE TRABAJO SOCIEDAD ANONIMA - Costa Rica | D14: No iniciada | E14: No iniciada | F14: No iniciada | G14: No iniciada | H14: No iniciada | I14: No iniciada | J14: No iniciada | K14: No iniciada | L14: No iniciada | M14: =COUNTIF(D14:K14,"Completada")/8 -> 0 | N14: 46496.75
A15: FIL-10 | B15: SERVICE TOTAL TALENT S.A. - Costa Rica | D15: No iniciada | E15: No iniciada | F15: No iniciada | G15: No iniciada | H15: No iniciada | I15: No iniciada | J15: No iniciada | K15: No iniciada | L15: No iniciada | M15: =COUNTIF(D15:K15,"Completada")/8 -> 0 | N15: 46496.75
A16: FIL-11 | B16: STT CONSULTING, S.A. - Costa Rica | D16: No iniciada | E16: No iniciada | F16: No iniciada | G16: No iniciada | H16: No iniciada | I16: No iniciada | J16: No iniciada | K16: No iniciada | L16: No iniciada | M16: =COUNTIF(D16:K16,"Completada")/8 -> 0 | N16: 46496.75
A17: FIL-12 | B17: S.T.T. CENTROAMERICA S.A. - Costa Rica | D17: No iniciada | E17: No iniciada | F17: No iniciada | G17: No iniciada | H17: No iniciada | I17: No iniciada | J17: No iniciada | K17: No iniciada | L17: No iniciada | M17: =COUNTIF(D17:K17,"Completada")/8 -> 0 | N17: 46496.75
... A40: FIL-35 | B40: SUPPLYING TOTAL TALENT S.A.S. - Argentina | D40: No iniciada | E40: No iniciada | F40: No iniciada | G40: No iniciada | H40: No iniciada | I40: No iniciada | J40: No iniciada | K40: No iniciada | L40: No iniciada | M40: =COUNTIF(D40:K40,"Completada")/8 -> 0 | N40: 46496.75

Sheet 04_Hitos_Entregables
A1: HITOS Y ENTREGABLES
A2: Cada hito requiere evidencia y aprobación formal.
A5: ID | B5: Hito | C5: Módulo | D5: Responsable | E5: Fecha plan | F5: Fecha real | G5: Estado | H5: Aprobado por | I5: Evidencia | J5: Dependencia | K5: Criterio | L5: Observaciones
A6: H-01 | B6: Acta de inicio aprobada | C6: Programa ERP | D6: Director de proyecto | E6: 46335.75 | G6: No iniciada | J6: Acta | K6: Acta de inicio aprobada con evidencia y aprobación.
A7: H-02 | B7: Ambiente de pruebas operativo | C7: Programa ERP | D7: Director de proyecto | E7: 46351.75 | G7: No iniciada | J7: H-01 | K7: Ambiente de pruebas operativo con evidencia y aprobación.
A8: H-03 | B8: Diseño CORE y Organización aprobado | C8: Programa ERP | D8: Director de proyecto | E8: 46367.75 | G8: No iniciada | J8: H-02 | K8: Diseño CORE y Organización aprobado con evidencia y aprobación.
A9: H-04 | B9: Matriz de seguridad aprobada | C9: Programa ERP | D9: Director de proyecto | E9: 46385.75 | G9: No iniciada | J9: H-03 | K9: Matriz de seguridad aprobada con evidencia y aprobación.
A10: H-05 | B10: Plan de cuentas aprobado | C10: Programa ERP | D10: Director de proyecto | E10: 46401.75 | G10: No iniciada | J10: H-04 | K10: Plan de cuentas aprobado con evidencia y aprobación.
A11: H-06 | B11: Diseño operativo aprobado | C11: Programa ERP | D11: Director de proyecto | E11: 46419.75 | G11: No iniciada | J11: H-05 | K11: Diseño operativo aprobado con evidencia y aprobación.
A12: H-07 | B12: Ensayo de migración 1 conciliado | C12: Programa ERP | D12: Director de proyecto | E12: 46435.75 | G12: No iniciada | J12: H-06 | K12: Ensayo de migración 1 conciliado con evidencia y aprobación.
A13: H-08 | B13: Pruebas integrales completadas | C13: Programa ERP | D13: Director de proyecto | E13: 46451.75 | G13: No iniciada | J13: H-07 | K13: Pruebas integrales completadas con evidencia y aprobación.
A14: H-09 | B14: Ensayo de migración 2 conciliado | C14: Programa ERP | D14: Director de proyecto | E14: 46469.75 | G14: No iniciada | J14: H-08 | K14: Ensayo de migración 2 conciliado con evidencia y aprobación.
A15: H-10 | B15: UAT aprobada | C15: Programa ERP | D15: Director de proyecto | E15: 46485.75 | G15: No iniciada | J15: H-09 | K15: UAT aprobada con evidencia y aprobación.
A16: H-11 | B16: Capacitación completada | C16: Programa ERP | D16: Director de proyecto | E16: 46503.75 | G16: No iniciada | J16: H-10 | K16: Capacitación completada con evidencia y aprobación.
A17: H-12 | B17: Ensayo de cutover aprobado | C17: Programa ERP | D17: Director de proyecto | E17: 46519.75 | G17: No iniciada | J17: H-11 | K17: Ensayo de cutover aprobado con evidencia y aprobación.
... A20: H-15 | B20: Cierre de estabilización | C20: Programa ERP | D20: Director de proyecto | E20: 46569.75 | G20: No iniciada | J20: H-14 | K20: Cierre de estabilización con evidencia y aprobación.

Sheet 05_Migracion_Datos
A1: PLAN DE MIGRACIÓN Y CONCILIACIÓN
A2: La salida exige diferencia 0,00 y conciliación firmada.
A5: ID | B5: Objeto | C5: Módulo | D5: Fuente | E5: Propietario | F5: Plantilla | G5: Corte | H5: Volumen | I5: Reg. origen | J5: Cargados | K5: Rechazados | L5: Diferencia | M5: Ensayo 1 | N5: Ensayo 2 | O5: Carga final | P5: Conciliación | Q5: Responsable | R5: Estado | S5: Evidencia | T5: Criterio
A6: MIG-01 | B6: Países monedas y zonas horarias | C6: CORE | D6: Por definir | E6: Dueño de datos | F6: Plantilla Países monedas y zonas horarias | L6: =IF(OR(I6="",J6=""),"",I6-J6-K6) | M6: No iniciada | N6: No iniciada | O6: No iniciada | P6: Pendiente | Q6: Consultor de datos | R6: No iniciada | T6: Registros válidos cargados y rechazados aprobados
A7: MIG-02 | B7: Subsidiarias y calendarios | C7: Organización | D7: Por definir | E7: Dueño de datos | F7: Plantilla Subsidiarias y calendarios | L7: =IF(OR(I7="",J7=""),"",I7-J7-K7) | M7: No iniciada | N7: No iniciada | O7: No iniciada | P7: Pendiente | Q7: Consultor de datos | R7: No iniciada | T7: Registros válidos cargados y rechazados aprobados
A8: MIG-03 | B8: Departamentos y jerarquías | C8: Organización | D8: Por definir | E8: Dueño de datos | F8: Plantilla Departamentos y jerarquías | L8: =IF(OR(I8="",J8=""),"",I8-J8-K8) | M8: No iniciada | N8: No iniciada | O8: No iniciada | P8: Pendiente | Q8: Consultor de datos | R8: No iniciada | T8: Registros válidos cargados y rechazados aprobados
A9: MIG-04 | B9: Centros de costos | C9: Organización | D9: Por definir | E9: Dueño de datos | F9: Plantilla Centros de costos | L9: =IF(OR(I9="",J9=""),"",I9-J9-K9) | M9: No iniciada | N9: No iniciada | O9: No iniciada | P9: Pendiente | Q9: Consultor de datos | R9: No iniciada | T9: Registros válidos cargados y rechazados aprobados
A10: MIG-05 | B10: Usuarios roles y empresas | C10: Seguridad | D10: Por definir | E10: Dueño de datos | F10: Plantilla Usuarios roles y empresas | L10: =IF(OR(I10="",J10=""),"",I10-J10-K10) | M10: No iniciada | N10: No iniciada | O10: No iniciada | P10: Pendiente | Q10: Consultor de datos | R10: No iniciada | T10: Registros válidos cargados y rechazados aprobados
A11: MIG-06 | B11: Plan de cuentas | C11: Contabilidad | D11: Por definir | E11: Dueño de datos | F11: Plantilla Plan de cuentas | L11: =IF(OR(I11="",J11=""),"",I11-J11-K11) | M11: No iniciada | N11: No iniciada | O11: No iniciada | P11: Pendiente | Q11: Consultor de datos | R11: No iniciada | T11: Registros válidos cargados y rechazados aprobados
A12: MIG-07 | B12: Libros y períodos | C12: Contabilidad | D12: Por definir | E12: Dueño de datos | F12: Plantilla Libros y períodos | L12: =IF(OR(I12="",J12=""),"",I12-J12-K12) | M12: No iniciada | N12: No iniciada | O12: No iniciada | P12: Pendiente | Q12: Consultor de datos | R12: No iniciada | T12: Registros válidos cargados y rechazados aprobados
A13: MIG-08 | B13: Impuestos y retenciones | C13: Configuración | D13: Por definir | E13: Dueño de datos | F13: Plantilla Impuestos y retenciones | L13: =IF(OR(I13="",J13=""),"",I13-J13-K13) | M13: No iniciada | N13: No iniciada | O13: No iniciada | P13: Pendiente | Q13: Consultor de datos | R13: No iniciada | T13: Registros válidos cargados y rechazados aprobados
A14: MIG-09 | B14: Tasas históricas | C14: Configuración | D14: Por definir | E14: Dueño de datos | F14: Plantilla Tasas históricas | L14: =IF(OR(I14="",J14=""),"",I14-J14-K14) | M14: No iniciada | N14: No iniciada | O14: No iniciada | P14: Pendiente | Q14: Consultor de datos | R14: No iniciada | T14: Registros válidos cargados y rechazados aprobados
A15: MIG-10 | B15: Clientes | C15: Entidades | D15: Por definir | E15: Dueño de datos | F15: Plantilla Clientes | L15: =IF(OR(I15="",J15=""),"",I15-J15-K15) | M15: No iniciada | N15: No iniciada | O15: No iniciada | P15: Pendiente | Q15: Consultor de datos | R15: No iniciada | T15: Registros válidos cargados y rechazados aprobados
A16: MIG-11 | B16: Proveedores | C16: Entidades | D16: Por definir | E16: Dueño de datos | F16: Plantilla Proveedores | L16: =IF(OR(I16="",J16=""),"",I16-J16-K16) | M16: No iniciada | N16: No iniciada | O16: No iniciada | P16: Pendiente | Q16: Consultor de datos | R16: No iniciada | T16: Registros válidos cargados y rechazados aprobados
A17: MIG-12 | B17: Empleados | C17: Entidades | D17: Por definir | E17: Dueño de datos | F17: Plantilla Empleados | L17: =IF(OR(I17="",J17=""),"",I17-J17-K17) | M17: No iniciada | N17: No iniciada | O17: No iniciada | P17: Pendiente | Q17: Consultor de datos | R17: No iniciada | T17: Registros válidos cargados y rechazados aprobados
... A32: MIG-27 | B32: Saldos intercompany | C32: Consolidación | D32: Por definir | E32: Dueño de datos | F32: Plantilla Saldos intercompany | L32: =IF(OR(I32="",J32=""),"",I32-J32-K32) | M32: No iniciada | N32: No iniciada | O32: No iniciada | P32: Pendiente | Q32: Consultor de datos | R32: No iniciada | T32: Registros válidos cargados y rechazados aprobados

Sheet 06_Pruebas_UAT
A1: PRUEBAS FUNCIONALES Y UAT
A2: No se autoriza Go-Live con defectos críticos abiertos.
A5: ID | B5: Módulo | C5: Proceso | D5: Escenario | E5: Precondición | F5: Pasos | G5: Resultado esperado | H5: Rol | I5: Subsidiaria | J5: Fecha | K5: Resultado | L5: Severidad | M5: Incidencia | N5: Re-prueba | O5: Evidencia | P5: Aprobado por
A6: UAT-001 | B6: CORE | C6: Países e identificadores ISO | D6: Escenario normal y de excepción de Países e identificadores ISO | E6: Maestros, permisos y período configurados | F6: 1) Levantar política para Países e identificadores ISO. 2) Preparar datos. 3) Parametrizar por filial. 4) Probar escenario normal, excepción y multimoneda cuando aplique. 5) Conciliar impacto y aprobar. | G6: Países e identificadores ISO funciona de extremo a extremo y contabiliza correctamente. | H6: Dueño de datos | I6: Piloto / filial asignada | K6: No ejecutado | L6: Sin defecto | N6: Pendiente | P6: Dueño de datos
A7: UAT-002 | B7: CORE | C7: Idiomas y zonas horarias | D7: Escenario normal y de excepción de Idiomas y zonas horarias | E7: Maestros, permisos y período configurados | F7: 1) Levantar política para Idiomas y zonas horarias. 2) Preparar datos. 3) Parametrizar por filial. 4) Probar escenario normal, excepción y multimoneda cuando aplique. 5) Conciliar impacto y aprobar. | G7: Idiomas y zonas horarias funciona de extremo a extremo y contabiliza correctamente. | H7: Dueño de datos | I7: Piloto / filial asignada | K7: No ejecutado | L7: Sin defecto | N7: Pendiente | P7: Dueño de datos
A8: UAT-003 | B8: CORE | C8: Monedas y precisión cambiaria | D8: Escenario normal y de excepción de Monedas y precisión cambiaria | E8: Maestros, permisos y período configurados | F8: 1) Levantar política para Monedas y precisión cambiaria. 2) Preparar datos. 3) Parametrizar por filial. 4) Probar escenario normal, excepción y multimoneda cuando aplique. 5) Conciliar impacto y aprobar. | G8: Monedas y precisión cambiaria funciona de extremo a extremo y contabiliza correctamente. | H8: Dueño de datos | I8: Piloto / filial asignada | K8: No ejecutado | L8: Sin defecto | N8: Pendiente | P8: Dueño de datos
A9: UAT-004 | B9: CORE | C9: Estados maestros | D9: Escenario normal y de excepción de Estados maestros | E9: Maestros, permisos y período configurados | F9: 1) Levantar política para Estados maestros. 2) Preparar datos. 3) Parametrizar por filial. 4) Probar escenario normal, excepción y multimoneda cuando aplique. 5) Conciliar impacto y aprobar. | G9: Estados maestros funciona de extremo a extremo y contabiliza correctamente. | H9: Dueño de datos | I9: Piloto / filial asignada | K9: No ejecutado | L9: Sin defecto | N9: Pendiente | P9: Dueño de datos
A10: UAT-005 | B10: CORE | C10: Tipos de transacción | D10: Escenario normal y de excepción de Tipos de transacción | E10: Maestros, permisos y período configurados | F10: 1) Levantar política para Tipos de transacción. 2) Preparar datos. 3) Parametrizar por filial. 4) Probar escenario normal, excepción y multimoneda cuando aplique. 5) Conciliar impacto y aprobar. | G10: Tipos de transacción funciona de extremo a extremo y contabiliza correctamente. | H10: Dueño de datos | I10: Piloto / filial asignada | K10: No ejecutado | L10: Sin defecto | N10: Pendiente | P10: Dueño de datos
A11: UAT-006 | B11: CORE | C11: Secuencias por filial y transacción | D11: Escenario normal y de excepción de Secuencias por filial y transacción | E11: Maestros, permisos y período configurados | F11: 1) Levantar política para Secuencias por filial y transacción. 2) Preparar datos. 3) Parametrizar por filial. 4) Probar escenario normal, excepción y multimoneda cuando aplique. 5) Conciliar impacto y aprobar. | G11: Secuencias por filial y transacción funciona de extremo a extremo y contabiliza correctamente. | H11: Dueño de datos | I11: Piloto / filial asignada | K11: No ejecutado | L11: Sin defecto | N11: Pendiente | P11: Dueño de datos
A12: UAT-007 | B12: CORE | C12: Prefijos, longitud y consecutivo inicial | D12: Escenario normal y de excepción de Prefijos, longitud y consecutivo inicial | E12: Maestros, permisos y período configurados | F12: 1) Levantar política para Prefijos, longitud y consecutivo inicial. 2) Preparar datos. 3) Parametrizar por filial. 4) Probar escenario normal, excepción y multimoneda cuando aplique. 5) Conciliar impacto y aprobar. | G12: Prefijos, longitud y consecutivo inicial funciona de extremo a extremo y contabiliza correctamente. | H12: Dueño de datos | I12: Piloto / filial asignada | K12: No ejecutado | L12: Sin defecto | N12: Pendiente | P12: Dueño de datos
A13: UAT-008 | B13: CORE | C13: Parámetros globales | D13: Escenario normal y de excepción de Parámetros globales | E13: Maestros, permisos y período configurados | F13: 1) Levantar política para Parámetros globales. 2) Preparar datos. 3) Parametrizar por filial. 4) Probar escenario normal, excepción y multimoneda cuando aplique. 5) Conciliar impacto y aprobar. | G13: Parámetros globales funciona de extremo a extremo y contabiliza correctamente. | H13: Dueño de datos | I13: Piloto / filial asignada | K13: No ejecutado | L13: Sin defecto | N13: Pendiente | P13: Dueño de datos
A14: UAT-009 | B14: CORE | C14: Configuraciones por alcance | D14: Escenario normal y de excepción de Configuraciones por alcance | E14: Maestros, permisos y período configurados | F14: 1) Levantar política para Configuraciones por alcance. 2) Preparar datos. 3) Parametrizar por filial. 4) Probar escenario normal, excepción y multimoneda cuando aplique. 5) Conciliar impacto y aprobar. | G14: Configuraciones por alcance funciona de extremo a extremo y contabiliza correctamente. | H14: Dueño de datos | I14: Piloto / filial asignada | K14: No ejecutado | L14: Sin defecto | N14: Pendiente | P14: Dueño de datos
A15: UAT-010 | B15: Organización | C15: Jerarquía de subsidiarias | D15: Escenario normal y de excepción de Jerarquía de subsidiarias | E15: Maestros, permisos y período configurados | F15: 1) Levantar política para Jerarquía de subsidiarias. 2) Preparar datos. 3) Parametrizar por filial. 4) Probar escenario normal, excepción y multimoneda cuando aplique. 5) Conciliar impacto y aprobar. | G15: Jerarquía de subsidiarias funciona de extremo a extremo y contabiliza correctamente. | H15: Contabilidad corporativa | I15: Piloto / filial asignada | K15: No ejecutado | L15: Sin defecto | N15: Pendiente | P15: Contabilidad corporativa
A16: UAT-011 | B16: Organización | C16: Años y calendarios fiscales | D16: Escenario normal y de excepción de Años y calendarios fiscales | E16: Maestros, permisos y período configurados | F16: 1) Levantar política para Años y calendarios fiscales. 2) Preparar datos. 3) Parametrizar por filial. 4) Probar escenario normal, excepción y multimoneda cuando aplique. 5) Conciliar impacto y aprobar. | G16: Años y calendarios fiscales funciona de extremo a extremo y contabiliza correctamente. | H16: Contabilidad corporativa | I16: Piloto / filial asignada | K16: No ejecutado | L16: Sin defecto | N16: Pendiente | P16: Contabilidad corporativa
A17: UAT-012 | B17: Organización | C17: Períodos contables | D17: Escenario normal y de excepción de Períodos contables | E17: Maestros, permisos y período configurados | F17: 1) Levantar política para Períodos contables. 2) Preparar datos. 3) Parametrizar por filial. 4) Probar escenario normal, excepción y multimoneda cuando aplique. 5) Conciliar impacto y aprobar. | G17: Períodos contables funciona de extremo a extremo y contabiliza correctamente. | H17: Contabilidad corporativa | I17: Piloto / filial asignada | K17: No ejecutado | L17: Sin defecto | N17: Pendiente | P17: Contabilidad corporativa
... A241: UAT-236 | B241: IA (opcional) | C241: Auditoría y confianza | D241: Escenario normal y de excepción de Auditoría y confianza | E241: Maestros, permisos y período configurados | F241: 1) Definir regla y responsables de Auditoría y confianza. 2) Configurar permisos, trazabilidad y excepciones. 3) Probar caso autorizado y no autorizado. 4) Revisar bitácora. 5) Obtener conformidad de Control Interno. | G241: Auditoría y confianza permite solo acciones autorizadas y registra actor, fecha y resultado. | H241: Comité de IA | I241: Piloto / filial asignada | K241: No ejecutado | L241: Sin defecto | N241: Pendiente | P241: Comité de IA

Sheet 07_Capacitacion
A1: PLAN DE CAPACITACIÓN
A2: Control de cobertura, evaluación y evidencia.
A5: ID | B5: Tema | C5: Audiencia | D5: Contenido | E5: Instructor | F5: Modalidad | G5: Fecha | H5: Horas | I5: Material | J5: Esperados | K5: Asistentes | L5: Cobertura | M5: Evaluación | N5: Estado | O5: Evidencia | P5: Observaciones
A6: CAP-01 | B6: Acceso y navegación | C6: Todos los usuarios | D6: Operación, controles, excepciones y práctica de Acceso y navegación | E6: Consultor GENTIA | F6: Virtual / presencial | G6: 46492.75 | H6: 2 | I6: Guía rápida y ejercicio | L6: =IFERROR(K6/J6,0) -> 0 | N6: No iniciada
A7: CAP-02 | B7: Usuarios roles y filiales | C7: Administradores | D7: Operación, controles, excepciones y práctica de Usuarios roles y filiales | E7: Consultor GENTIA | F7: Virtual / presencial | G7: 46496.75 | H7: 2 | I7: Guía rápida y ejercicio | L7: =IFERROR(K7/J7,0) -> 0 | N7: No iniciada
A8: CAP-03 | B8: CORE y Organización | C8: Administradores funcionales | D8: Operación, controles, excepciones y práctica de CORE y Organización | E8: Consultor GENTIA | F8: Virtual / presencial | G8: 46498.75 | H8: 2 | I8: Guía rápida y ejercicio | L8: =IFERROR(K8/J8,0) -> 0 | N8: No iniciada
A9: CAP-04 | B9: Contabilidad y cierres | C9: Contadores | D9: Operación, controles, excepciones y práctica de Contabilidad y cierres | E9: Consultor GENTIA | F9: Virtual / presencial | G9: 46500.75 | H9: 2 | I9: Guía rápida y ejercicio | L9: =IFERROR(K9/J9,0) -> 0 | N9: No iniciada
A10: CAP-05 | B10: Saldos iniciales | C10: Migración / Contabilidad | D10: Operación, controles, excepciones y práctica de Saldos iniciales | E10: Consultor GENTIA | F10: Virtual / presencial | G10: 46504.75 | H10: 2 | I10: Guía rápida y ejercicio | L10: =IFERROR(K10/J10,0) -> 0 | N10: No iniciada
A11: CAP-06 | B11: Ventas y CxC | C11: Ventas / CxC | D11: Operación, controles, excepciones y práctica de Ventas y CxC | E11: Consultor GENTIA | F11: Virtual / presencial | G11: 46506.75 | H11: 2 | I11: Guía rápida y ejercicio | L11: =IFERROR(K11/J11,0) -> 0 | N11: No iniciada
A12: CAP-07 | B12: Compras y CxP | C12: Compras / CxP | D12: Operación, controles, excepciones y práctica de Compras y CxP | E12: Consultor GENTIA | F12: Virtual / presencial | G12: 46510.75 | H12: 2 | I12: Guía rápida y ejercicio | L12: =IFERROR(K12/J12,0) -> 0 | N12: No iniciada
A13: CAP-08 | B13: Solicitudes de pago | C13: Solicitantes / Tesorería | D13: Operación, controles, excepciones y práctica de Solicitudes de pago | E13: Consultor GENTIA | F13: Virtual / presencial | G13: 46512.75 | H13: 2 | I13: Guía rápida y ejercicio | L13: =IFERROR(K13/J13,0) -> 0 | N13: No iniciada
A14: CAP-09 | B14: Aprobaciones | C14: Aprobadores | D14: Operación, controles, excepciones y práctica de Aprobaciones | E14: Consultor GENTIA | F14: Virtual / presencial | G14: 46514.75 | H14: 2 | I14: Guía rápida y ejercicio | L14: =IFERROR(K14/J14,0) -> 0 | N14: No iniciada
A15: CAP-10 | B15: Bancos y conciliación | C15: Tesorería | D15: Operación, controles, excepciones y práctica de Bancos y conciliación | E15: Consultor GENTIA | F15: Virtual / presencial | G15: 46518.75 | H15: 2 | I15: Guía rápida y ejercicio | L15: =IFERROR(K15/J15,0) -> 0 | N15: No iniciada
A16: CAP-11 | B16: Tesorería y pagos | C16: Tesorería | D16: Operación, controles, excepciones y práctica de Tesorería y pagos | E16: Consultor GENTIA | F16: Virtual / presencial | G16: 46520.75 | H16: 2 | I16: Guía rápida y ejercicio | L16: =IFERROR(K16/J16,0) -> 0 | N16: No iniciada
A17: CAP-12 | B17: Activos Fijos | C17: Responsable de activos | D17: Operación, controles, excepciones y práctica de Activos Fijos | E17: Consultor GENTIA | F17: Virtual / presencial | G17: 46524.75 | H17: 2 | I17: Guía rápida y ejercicio | L17: =IFERROR(K17/J17,0) -> 0 | N17: No iniciada
... A24: CAP-19 | B24: Soporte | C24: Mesa de ayuda | D24: Operación, controles, excepciones y práctica de Soporte | E24: Consultor GENTIA | F24: Virtual / presencial | G24: 46542.75 | H24: 2 | I24: Guía rápida y ejercicio | L24: =IFERROR(K24/J24,0) -> 0 | N24: No iniciada

Sheet 08_RACI
A1: MATRIZ RACI
A2: R Responsable · A Aprobador · C Consultado · I Informado.
A5: Proceso | B5: Patrocinador | C5: Director proyecto | D5: Contabilidad | E5: Compras/CxP | F5: Ventas/CxC | G5: Tesorería | H5: Impuestos | I5: TI/Seguridad | J5: Auditoría | K5: Consultor GENTIA | L5: Usuario clave
A6: Gobierno y alcance | B6: A | C6: R | D6: C | E6: C | F6: C | G6: C | H6: C | I6: C | J6: C | K6: C | L6: C
A7: Infraestructura | B7: C | C7: A | D7: R | E7: C | F7: C | G7: C | H7: C | I7: C | J7: C | K7: C | L7: C
A8: Seguridad | B8: C | C8: C | D8: A | E8: R | F8: C | G8: C | H8: C | I8: C | J8: C | K8: C | L8: C
A9: CORE y secuencias | B9: C | C9: C | D9: C | E9: A | F9: R | G9: C | H9: C | I9: C | J9: C | K9: C | L9: C
A10: Organización y dimensiones | B10: C | C10: C | D10: C | E10: C | F10: A | G10: R | H10: C | I10: C | J10: C | K10: C | L10: C
A11: Plan de cuentas | B11: C | C11: C | D11: C | E11: C | F11: C | G11: A | H11: R | I11: C | J11: C | K11: C | L11: C
A12: Impuestos | B12: C | C12: C | D12: C | E12: C | F12: C | G12: C | H12: A | I12: R | J12: C | K12: C | L12: C
A13: Clientes y CxC | B13: C | C13: C | D13: C | E13: C | F13: C | G13: C | H13: C | I13: A | J13: R | K13: C | L13: C
A14: Proveedores y CxP | B14: C | C14: C | D14: C | E14: C | F14: C | G14: C | H14: C | I14: C | J14: A | K14: R | L14: C
A15: Ventas | B15: C | C15: C | D15: C | E15: C | F15: C | G15: C | H15: C | I15: C | J15: C | K15: A | L15: R
A16: Compras | B16: R | C16: C | D16: C | E16: C | F16: C | G16: C | H16: C | I16: C | J16: C | K16: C | L16: A
... A31: Hypercare | B31: C | C31: C | D31: C | E31: A | F31: R | G31: C | H31: C | I31: C | J31: C | K31: C | L31: C

Sheet 09_Riesgos
A1: RIESGOS, INCIDENCIAS Y DECISIONES
A2: Puntaje 15 o superior requiere revisión del comité.
A5: ID | B5: Tipo | C5: Descripción | D5: Módulo | E5: Causa | F5: Impacto | G5: Prob. | H5: Impacto | I5: Estrategia | J5: Mitigación | K5: Responsable | L5: Puntaje | M5: Compromiso | N5: Estado | O5: Cierre | P5: Evidencia | Q5: Observaciones
A6: R-01 | B6: Riesgo | C6: Datos fuente incompletos | D6: Migración de datos | E6: Por analizar | F6: Impacto en cronograma, control o salida | G6: 5 | H6: 4 | I6: Mitigar | J6: Definir acción preventiva, responsable y fecha | K6: Dueño de proceso | L6: =G6*H6 -> 20 | M6: 46370.75 | N6: Abierto
A7: R-02 | B7: Riesgo | C7: Plan de cuentas tardío | D7: Contabilidad | E7: Por analizar | F7: Impacto en cronograma, control o salida | G7: 5 | H7: 4 | I7: Mitigar | J7: Definir acción preventiva, responsable y fecha | K7: Dueño de proceso | L7: =G7*H7 -> 20 | M7: 46374.75 | N7: Abierto
A8: R-03 | B8: Riesgo | C8: Mayor no concilia con auxiliares | D8: Migración de datos | E8: Por analizar | F8: Impacto en cronograma, control o salida | G8: 5 | H8: 4 | I8: Mitigar | J8: Definir acción preventiva, responsable y fecha | K8: Dueño de proceso | L8: =G8*H8 -> 20 | M8: 46380.75 | N8: Abierto
A9: R-04 | B9: Riesgo | C9: Usuarios no disponibles para UAT | D9: Pruebas | E9: Por analizar | F9: Impacto en cronograma, control o salida | G9: 4 | H9: 4 | I9: Mitigar | J9: Definir acción preventiva, responsable y fecha | K9: Dueño de proceso | L9: =G9*H9 -> 16 | M9: 46386.75 | N9: Abierto
A10: R-05 | B10: Riesgo | C10: Permisos excesivos | D10: Seguridad | E10: Por analizar | F10: Impacto en cronograma, control o salida | G10: 5 | H10: 3 | I10: Mitigar | J10: Definir acción preventiva, responsable y fecha | K10: Dueño de proceso | L10: =G10*H10 -> 15 | M10: 46392.75 | N10: Abierto
A11: R-06 | B11: Riesgo | C11: Tasas o impuestos incorrectos | D11: Configuración | E11: Por analizar | F11: Impacto en cronograma, control o salida | G11: 5 | H11: 4 | I11: Mitigar | J11: Definir acción preventiva, responsable y fecha | K11: Dueño de proceso | L11: =G11*H11 -> 20 | M11: 46398.75 | N11: Abierto
A12: R-07 | B12: Riesgo | C12: Consecutivos incorrectos | D12: CORE | E12: Por analizar | F12: Impacto en cronograma, control o salida | G12: 4 | H12: 3 | I12: Mitigar | J12: Definir acción preventiva, responsable y fecha | K12: Dueño de proceso | L12: =G12*H12 -> 12 | M12: 46402.75 | N12: Abierto
A13: R-08 | B13: Riesgo | C13: SMTP o URLs incompletas | D13: Infraestructura | E13: Por analizar | F13: Impacto en cronograma, control o salida | G13: 4 | H13: 3 | I13: Mitigar | J13: Definir acción preventiva, responsable y fecha | K13: Dueño de proceso | L13: =G13*H13 -> 12 | M13: 46408.75 | N13: Abierto
A14: R-09 | B14: Riesgo | C14: Timeouts por volumen | D14: Infraestructura | E14: Por analizar | F14: Impacto en cronograma, control o salida | G14: 4 | H14: 3 | I14: Mitigar | J14: Definir acción preventiva, responsable y fecha | K14: Dueño de proceso | L14: =G14*H14 -> 12 | M14: 46414.75 | N14: Abierto
A15: R-10 | B15: Riesgo | C15: Dimensiones mal asociadas | D15: Organización | E15: Por analizar | F15: Impacto en cronograma, control o salida | G15: 4 | H15: 4 | I15: Mitigar | J15: Definir acción preventiva, responsable y fecha | K15: Dueño de proceso | L15: =G15*H15 -> 16 | M15: 46420.75 | N15: Abierto
A16: R-11 | B16: Riesgo | C16: Aprobadores inactivos | D16: Workflow | E16: Por analizar | F16: Impacto en cronograma, control o salida | G16: 4 | H16: 3 | I16: Mitigar | J16: Definir acción preventiva, responsable y fecha | K16: Dueño de proceso | L16: =G16*H16 -> 12 | M16: 46426.75 | N16: Abierto
A17: R-12 | B17: Riesgo | C17: Saldos intercompany distintos | D17: Consolidación | E17: Por analizar | F17: Impacto en cronograma, control o salida | G17: 5 | H17: 4 | I17: Mitigar | J17: Definir acción preventiva, responsable y fecha | K17: Dueño de proceso | L17: =G17*H17 -> 20 | M17: 46430.75 | N17: Abierto
... A22: R-17 | B22: Riesgo | C22: Respaldos no restaurables | D22: Infraestructura | E22: Por analizar | F22: Impacto en cronograma, control o salida | G22: 5 | H22: 3 | I22: Mitigar | J22: Definir acción preventiva, responsable y fecha | K22: Dueño de proceso | L22: =G22*H22 -> 15 | M22: 46458.75 | N22: Abierto

Sheet 10_Cutover_GoLive
A1: CUTOVER Y GO-LIVE
A2: Secuencia con validación, reversión y decisión Go/No-Go.
A5: ID | B5: Momento | C5: Tipo | D5: Actividad | E5: Validación | F5: Dependencia | G5: Responsable | H5: Inicio plan | I5: Fin plan | J5: Inicio real | K5: Fin real | L5: Estado | M5: Resultado | N5: Rollback | O5: Evidencia | P5: Go/No-Go
A6: CUT-01 | B6: T-30 | C6: Control | D6: Confirmar alcance y congelamiento | E6: Ejecutar confirmar alcance y congelamiento, registrar resultado y evidencia. | F6: UAT aprobada | G6: Director de proyecto | H6: 46466.75 | I6: 46466.75 | L6: No iniciada | M6: Pendiente | N6: Aplicar rollback aprobado | P6: Pendiente
A7: CUT-02 | B7: T-29 | C7: Control | D7: Aprobar fuentes y plantillas | E7: Ejecutar aprobar fuentes y plantillas, registrar resultado y evidencia. | F7: CUT-01 | G7: Director de proyecto | H7: 46467.75 | I7: 46467.75 | L7: No iniciada | M7: Pendiente | N7: Aplicar rollback aprobado | P7: Pendiente
A8: CUT-03 | B8: T-28 | C8: Control | D8: Probar restauración y rollback | E8: Ejecutar probar restauración y rollback, registrar resultado y evidencia. | F8: CUT-02 | G8: Director de proyecto | H8: 46468.75 | I8: 46468.75 | L8: No iniciada | M8: Pendiente | N8: Aplicar rollback aprobado | P8: Pendiente
A9: CUT-04 | B9: T-27 | C9: Control | D9: Cerrar defectos críticos | E9: Ejecutar cerrar defectos críticos, registrar resultado y evidencia. | F9: CUT-03 | G9: Director de proyecto | H9: 46469.75 | I9: 46469.75 | L9: No iniciada | M9: Pendiente | N9: Aplicar rollback aprobado | P9: Pendiente
A10: CUT-05 | B10: T-26 | C10: Control | D10: Completar capacitaciones | E10: Ejecutar completar capacitaciones, registrar resultado y evidencia. | F10: CUT-04 | G10: Director de proyecto | H10: 46470.75 | I10: 46470.75 | L10: No iniciada | M10: Pendiente | N10: Aplicar rollback aprobado | P10: Pendiente
A11: CUT-06 | B11: T-25 | C11: Control | D11: Ejecutar ensayo general | E11: Ejecutar ejecutar ensayo general, registrar resultado y evidencia. | F11: CUT-05 | G11: Director de proyecto | H11: 46471.75 | I11: 46471.75 | L11: No iniciada | M11: Pendiente | N11: Aplicar rollback aprobado | P11: Pendiente
A12: CUT-07 | B12: T-24 | C12: Control | D12: Conciliar ensayo | E12: Ejecutar conciliar ensayo, registrar resultado y evidencia. | F12: CUT-06 | G12: Director de proyecto | H12: 46472.75 | I12: 46472.75 | L12: No iniciada | M12: Pendiente | N12: Aplicar rollback aprobado | P12: Pendiente
A13: CUT-08 | B13: T-23 | C13: Control | D13: Aprobar accesos productivos | E13: Ejecutar aprobar accesos productivos, registrar resultado y evidencia. | F13: CUT-07 | G13: Director de proyecto | H13: 46473.75 | I13: 46473.75 | L13: No iniciada | M13: Pendiente | N13: Aplicar rollback aprobado | P13: Pendiente
A14: CUT-09 | B14: T-22 | C14: Control | D14: Validar dominio SMTP y monitoreo | E14: Ejecutar validar dominio smtp y monitoreo, registrar resultado y evidencia. | F14: CUT-08 | G14: Director de proyecto | H14: 46474.75 | I14: 46474.75 | L14: No iniciada | M14: Pendiente | N14: Aplicar rollback aprobado | P14: Pendiente
A15: CUT-10 | B15: T-21 | C15: Control | D15: Aprobar PDF y reportes | E15: Ejecutar aprobar pdf y reportes, registrar resultado y evidencia. | F15: CUT-09 | G15: Director de proyecto | H15: 46475.75 | I15: 46475.75 | L15: No iniciada | M15: Pendiente | N15: Aplicar rollback aprobado | P15: Pendiente
A16: CUT-11 | B16: T-20 | C16: Control | D16: Comité preliminar Go/No-Go | E16: Ejecutar comité preliminar go/no-go, registrar resultado y evidencia. | F16: CUT-10 | G16: Director de proyecto | H16: 46476.75 | I16: 46476.75 | L16: No iniciada | M16: Pendiente | N16: Aplicar rollback aprobado | P16: Pendiente
A17: CUT-12 | B17: T-19 | C17: Control | D17: Comunicar congelamiento | E17: Ejecutar comunicar congelamiento, registrar resultado y evidencia. | F17: CUT-11 | G17: Director de proyecto | H17: 46477.75 | I17: 46477.75 | L17: No iniciada | M17: Pendiente | N17: Aplicar rollback aprobado | P17: Pendiente
... A42: CUT-37 | B42: T+12 | C42: Control | D42: Cerrar Hypercare | E42: Ejecutar cerrar hypercare, registrar resultado y evidencia. | F42: CUT-36 | G42: Director de proyecto | H42: 46508.75 | I42: 46508.75 | L42: No iniciada | M42: Pendiente | N42: Aplicar rollback aprobado | P42: Pendiente

Sheet 11_Estabilizacion
A1: ESTABILIZACIÓN E HYPERCARE
A2: Incidencias, SLA, causa raíz y prevención post salida.
A5: ID | B5: Tipo | C5: Módulo | D5: Descripción | E5: Criticidad | F5: Reporte | G5: SLA h | H5: Responsable | I5: Estado | J5: Objetivo | K5: Cierre | L5: Solución | M5: Causa raíz | N5: Prevención | O5: Evidencia | P5: Cumplió SLA | Q5: Observaciones
A6: EST-01 | B6: Control preventivo | C6: Operación / Plataforma | D6: Monitorear accesos | E6: Alta | F6: 46496.75 | G6: 24 | H6: Mesa de ayuda | I6: Abierto | J6: 46497.75 | P6: =IF(OR(F6="",K6=""),"",IF((K6-F6)*24<=G6,"Sí","No"))
A7: EST-02 | B7: Control preventivo | C7: Operación / Plataforma | D7: Revisar facturas de venta | E7: Alta | F7: 46497.75 | G7: 24 | H7: Mesa de ayuda | I7: Abierto | J7: 46498.75 | P7: =IF(OR(F7="",K7=""),"",IF((K7-F7)*24<=G7,"Sí","No"))
A8: EST-03 | B8: Control preventivo | C8: Operación / Plataforma | D8: Revisar facturas de proveedor | E8: Alta | F8: 46498.75 | G8: 24 | H8: Mesa de ayuda | I8: Abierto | J8: 46499.75 | P8: =IF(OR(F8="",K8=""),"",IF((K8-F8)*24<=G8,"Sí","No"))
A9: EST-04 | B9: Control preventivo | C9: Operación / Plataforma | D9: Validar cobros y pagos | E9: Alta | F9: 46499.75 | G9: 24 | H9: Mesa de ayuda | I9: Abierto | J9: 46500.75 | P9: =IF(OR(F9="",K9=""),"",IF((K9-F9)*24<=G9,"Sí","No"))
A10: EST-05 | B10: Control preventivo | C10: Operación / Plataforma | D10: Validar asientos automáticos | E10: Alta | F10: 46500.75 | G10: 24 | H10: Mesa de ayuda | I10: Abierto | J10: 46501.75 | P10: =IF(OR(F10="",K10=""),"",IF((K10-F10)*24<=G10,"Sí","No"))
A11: EST-06 | B11: Control preventivo | C11: Operación / Plataforma | D11: Conciliar bancos | E11: Alta | F11: 46501.75 | G11: 24 | H11: Mesa de ayuda | I11: Abierto | J11: 46502.75 | P11: =IF(OR(F11="",K11=""),"",IF((K11-F11)*24<=G11,"Sí","No"))
A12: EST-07 | B12: Control preventivo | C12: Operación / Plataforma | D12: Revisar estados financieros | E12: Alta | F12: 46502.75 | G12: 24 | H12: Mesa de ayuda | I12: Abierto | J12: 46503.75 | P12: =IF(OR(F12="",K12=""),"",IF((K12-F12)*24<=G12,"Sí","No"))
A13: EST-08 | B13: Control preventivo | C13: Operación / Plataforma | D13: Revisar aprobaciones | E13: Alta | F13: 46503.75 | G13: 24 | H13: Mesa de ayuda | I13: Abierto | J13: 46504.75 | P13: =IF(OR(F13="",K13=""),"",IF((K13-F13)*24<=G13,"Sí","No"))
A14: EST-09 | B14: Control preventivo | C14: Operación / Plataforma | D14: Monitorear rendimiento | E14: Alta | F14: 46504.75 | G14: 24 | H14: Mesa de ayuda | I14: Abierto | J14: 46505.75 | P14: =IF(OR(F14="",K14=""),"",IF((K14-F14)*24<=G14,"Sí","No"))
A15: EST-10 | B15: Control preventivo | C15: Operación / Plataforma | D15: Conciliar primera semana | E15: Alta | F15: 46505.75 | G15: 24 | H15: Mesa de ayuda | I15: Abierto | J15: 46506.75 | P15: =IF(OR(F15="",K15=""),"",IF((K15-F15)*24<=G15,"Sí","No"))
A16: EST-11 | B16: Control preventivo | C16: Operación / Plataforma | D16: Revisar backlog | E16: Alta | F16: 46506.75 | G16: 24 | H16: Mesa de ayuda | I16: Abierto | J16: 46507.75 | P16: =IF(OR(F16="",K16=""),"",IF((K16-F16)*24<=G16,"Sí","No"))
A17: EST-12 | B17: Control preventivo | C17: Operación / Plataforma | D17: Transferir a soporte | E17: Alta | F17: 46507.75 | G17: 24 | H17: Mesa de ayuda | I17: Abierto | J17: 46508.75 | P17: =IF(OR(F17="",K17=""),"",IF((K17-F17)*24<=G17,"Sí","No"))
A18: EST-13 | B18: Incidencia | G18: 24 | H18: Mesa de ayuda | I18: Abierto | P18: =IF(OR(F18="",K18=""),"",IF((K18-F18)*24<=G18,"Sí","No"))
A19: EST-14 | B19: Incidencia | G19: 24 | H19: Mesa de ayuda | I19: Abierto | P19: =IF(OR(F19="",K19=""),"",IF((K19-F19)*24<=G19,"Sí","No"))
A20: EST-15 | B20: Incidencia | G20: 24 | H20: Mesa de ayuda | I20: Abierto | P20: =IF(OR(F20="",K20=""),"",IF((K20-F20)*24<=G20,"Sí","No"))
A21: EST-16 | B21: Incidencia | G21: 24 | H21: Mesa de ayuda | I21: Abierto | P21: =IF(OR(F21="",K21=""),"",IF((K21-F21)*24<=G21,"Sí","No"))
A22: EST-17 | B22: Incidencia | G22: 24 | H22: Mesa de ayuda | I22: Abierto | P22: =IF(OR(F22="",K22=""),"",IF((K22-F22)*24<=G22,"Sí","No"))
A23: EST-18 | B23: Incidencia | G23: 24 | H23: Mesa de ayuda | I23: Abierto | P23: =IF(OR(F23="",K23=""),"",IF((K23-F23)*24<=G23,"Sí","No"))
A24: EST-19 | B24: Incidencia | G24: 24 | H24: Mesa de ayuda | I24: Abierto | P24: =IF(OR(F24="",K24=""),"",IF((K24-F24)*24<=G24,"Sí","No"))
A25: EST-20 | B25: Incidencia | G25: 24 | H25: Mesa de ayuda | I25: Abierto | P25: =IF(OR(F25="",K25=""),"",IF((K25-F25)*24<=G25,"Sí","No"))
A26: EST-21 | B26: Incidencia | G26: 24 | H26: Mesa de ayuda | I26: Abierto | P26: =IF(OR(F26="",K26=""),"",IF((K26-F26)*24<=G26,"Sí","No"))
A27: EST-22 | B27: Incidencia | G27: 24 | H27: Mesa de ayuda | I27: Abierto | P27: =IF(OR(F27="",K27=""),"",IF((K27-F27)*24<=G27,"Sí","No"))
A28: EST-23 | B28: Incidencia | G28: 24 | H28: Mesa de ayuda | I28: Abierto | P28: =IF(OR(F28="",K28=""),"",IF((K28-F28)*24<=G28,"Sí","No"))
A29: EST-24 | B29: Incidencia | G29: 24 | H29: Mesa de ayuda | I29: Abierto | P29: =IF(OR(F29="",K29=""),"",IF((K29-F29)*24<=G29,"Sí","No"))
... A45: EST-40 | B45: Incidencia | G45: 24 | H45: Mesa de ayuda | I45: Abierto | P45: =IF(OR(F45="",K45=""),"",IF((K45-F45)*24<=G45,"Sí","No"))

Sheet 99_Listas
A1: Estados | B1: Prioridad | C1: Sí/No | D1: UAT | E1: Severidad | F1: Responsables | G1: RACI | H1: Estado riesgo | I1: Etapa filial | J1: Estrategia | K1: Módulos | L1: Modalidad
A2: No iniciada | B2: Crítica | C2: Sí | D2: No ejecutado | E2: Sin defecto | F2: Patrocinador ejecutivo | G2: R | H2: Abierto | I2: No iniciada | J2: Mitigar | K2: Gobierno del proyecto | L2: Virtual
A3: En curso | B3: Alta | C3: No | D3: Aprobado | E3: Crítica | F3: Director de proyecto | G3: A | H3: En seguimiento | I3: En curso | J3: Evitar | K3: Infraestructura y plataforma | L3: Presencial
A4: En validación | B4: Media | D4: Fallido | E4: Alta | F4: Líder funcional GENTIA | G4: C | H4: Cerrado | I4: En validación | J4: Transferir | K4: CORE | L4: Virtual / presencial
A5: Bloqueada | B5: Baja | D5: Bloqueado | E5: Media | F5: Líder técnico | G5: I | H5: Aceptado | I5: Bloqueada | J5: Aceptar | K5: Organización
A6: Completada | D6: Pendiente | E6: Baja | F6: Consultor funcional | I6: Completada | K6: Seguridad
A7: No aplica | F7: Consultor de datos | I7: No aplica | K7: Configuración transversal
F8: Consultor fiscal | K8: Contabilidad
F9: Consultor de consolidación | K9: Motor de transacciones
F10: Administrador de seguridad | K10: Entidades
F11: Contabilidad | K11: Ventas y Cuentas por Cobrar
F12: Tesorería | K12: Compras y Cuentas por Pagar
F13: Impuestos | K13: Gastos
F14: Dueño de datos | K14: Workflow y aprobaciones
F15: Dueño de proceso | K15: Bancos
F16: Usuario clave | K16: Tesorería
F17: Mesa de ayuda | K17: Activos Fijos
K18: Inventario
K19: Fiscal
K20: Intercompany y Consolidación
K21: Documentos
K22: Auditoría
K23: Informes
K24: IA (opcional)
K25: Migración de datos
K26: Pruebas formación y salida
